<?xml version="1.0" encoding="UTF-8"?>
<Jornada>
	<Jornada>
		<Numero>1487</Numero>
		<Fecha>230130</Fecha>
		<Documentos type="list">
			<Documento>
				<Orden>0</Orden>
				<Items type="list">
					<Cliente>
						<Orden>0</Orden>
						<NroDocumento>1</NroDocumento>
						<NroSecuencia>1</NroSecuencia>
						<TipoDocumento>DNI</TipoDocumento>
						<TipoCliente>ClienteConsumidorFinal</TipoCliente>
						<Nombre>CONSUMIDOR FINAL</Nombre>
						<Direccion>.</Direccion>
					</Cliente>
					<AtributosImpresion>
						<Orden>1</Orden>
						<Personalidad>ImpresorFiscal</Personalidad>
						<Producto>SMH/PT-250F 6.02A</Producto>
						<Modelo>Hasar SMH/PT-250F 1.</Modelo>
						<ModeloImpresor>80250-64</ModeloImpresor>
						<Estacion>Ticket</Estacion>
						<AnchoPapel>64</AnchoPapel>
						<AltoPapel>0</AltoPapel>
						<TipoHojaAlto>AltoA4</TipoHojaAlto>
						<TipoHojaAncho>AnchoNormal</TipoHojaAncho>
						<ImprimeLeyendasOpcionales>Sí</ImprimeLeyendasOpcionales>
						<ImprimeCodigos>NoImprimeCodigos</ImprimeCodigos>
						<ImprimeUnidadesMedida>No</ImprimeUnidadesMedida>
						<ImprimeMarcos>No</ImprimeMarcos>
						<ModoEntrenamiento>No</ModoEntrenamiento>
						<SignoMonetario>$</SignoMonetario>
						<UsarColorAlternativo>No</UsarColorAlternativo>
						<ColorAlternativo>Negro</ColorAlternativo>
						<ImprimeQR>Sí</ImprimeQR>
						<TipoInterlineado>InterlineadoNormal</TipoInterlineado>
					</AtributosImpresion>
					<Emisor>
						<Orden>2</Orden>
						<CUIT>20347825604</CUIT>
						<RazonSocial>COLANERI SERGIO ALEJANDRO</RazonSocial>
						<NroRegistro>HSHSAB0000009658</NroRegistro>
						<FechaInicioActividades>20180901</FechaInicioActividades>
						<IngBrutos>20-34782560-4</IngBrutos>
						<TipoEmisor>EmisorInscripto</TipoEmisor>
						<TipoHabilitacion>ComprobantesA</TipoHabilitacion>
						<LimiteM>1000</LimiteM>
					</Emisor>
					<LineaUsuario>
						<Orden>3</Orden>
						<Estacion>Ticket</Estacion>
						<Tipo>OwnerAddress</Tipo>
						<Linea>1</Linea>
						<Texto>
							<Texto>CALLE 16 ESQ 19</Texto>
							<Atributos type="list">
							</Atributos>
						</Texto>
					</LineaUsuario>
					<LineaUsuario>
						<Orden>4</Orden>
						<Estacion>Ticket</Estacion>
						<Tipo>OwnerAddress</Tipo>
						<Linea>2</Linea>
						<Texto>
							<Texto>C.P.(3700)-PCIA. R. S. PEÑA-CHACO</Texto>
							<Atributos type="list">
							</Atributos>
						</Texto>
					</LineaUsuario>
					<LineaUsuario>
						<Orden>5</Orden>
						<Estacion>Ticket</Estacion>
						<Tipo>Fantasy</Tipo>
						<Linea>1</Linea>
						<Texto>
							<Texto>ÑANDEJARA CARNES</Texto>
							<Atributos type="list">
							</Atributos>
						</Texto>
					</LineaUsuario>
					<Apertura>
						<Orden>6</Orden>
						<TipoDocumento>DocumentoFiscal</TipoDocumento>
						<SubTipoDocumento>Factura</SubTipoDocumento>
						<CalificadorDocumento>B</CalificadorDocumento>
						<Estacion>Ticket</Estacion>
						<TipoAFIP>82</TipoAFIP>
						<POS>00011</POS>
						<Fecha>230130</Fecha>
						<Hora>173329</Hora>
						<NumeroDocumento>54745</NumeroDocumento>
						<NumeroCompleto>00011-00054745</NumeroCompleto>
						<IdentificadorCopia>Original</IdentificadorCopia>
					</Apertura>
					<Venta>
						<Orden>7</Orden>
						<Descripcion>PECETO DE TERNERA</Descripcion>
						<CodigoInterno>00231</CodigoInterno>
						<CodigoMatrix>00231</CodigoMatrix>
						<Cantidad>2.925</Cantidad>
						<UnidadesMatrix>0</UnidadesMatrix>
						<UnidadMedida>UM_KILO</UnidadMedida>
						<Precio>1656.742</Precio>
						<CondicionIVA>CondicionIVAGravado</CondicionIVA>
						<TasaIVA>10.5</TasaIVA>
						<ImpuestoComoCoeficiente>Sí</ImpuestoComoCoeficiente>
						<ImpInt>0</ImpInt>
						<ImpIntFijo>No</ImpIntFijo>
						<PorBaseImponible>No</PorBaseImponible>
						<Desglose>
							<Cantidad>2.925</Cantidad>
							<PrecioFinal>1656.742</PrecioFinal>
							<MontoFinal>4845.97</MontoFinal>
							<TasaIVA>10.5</TasaIVA>
							<PrecioBase>1499.314</PrecioBase>
							<MontoTotalBase>4385.49</MontoTotalBase>
							<MontoTotalIVA>460.48</MontoTotalIVA>
							<MontoTotalII>0</MontoTotalII>
							<ImpIntFijo>No</ImpIntFijo>
							<ConceptosNoGravados>0</ConceptosNoGravados>
							<K>0</K>
						</Desglose>
					</Venta>
					<DiscriminacionIVA>
						<Orden>8</Orden>
						<CondicionIVA>CondicionIVAGravado</CondicionIVA>
						<TasaIVA>10.5</TasaIVA>
						<Base>4385.49</Base>
						<MontoIVA>460.48</MontoIVA>
					</DiscriminacionIVA>
					<Totales>
						<Orden>9</Orden>
						<Base>4385.49</Base>
						<MontoIVA>460.48</MontoIVA>
						<MontoII>0</MontoII>
						<MontoOtrosTributos>0</MontoOtrosTributos>
						<MontoNoGravado>0</MontoNoGravado>
						<MontoExento>0</MontoExento>
						<MontoGravado>4385.49</MontoGravado>
						<AjusteRedondeo>0</AjusteRedondeo>
						<Final>4845.97</Final>
						<ImpresionBase>4385.49</ImpresionBase>
						<ImpresionMontoIVA>460.48</ImpresionMontoIVA>
						<ImpresionMontoII>0</ImpresionMontoII>
						<ImpresionFinal>4845.97</ImpresionFinal>
						<TipoTotales>TotalesAlFinal</TipoTotales>
					</Totales>
					<Pago>
						<Orden>10</Orden>
						<EsCambio>No</EsCambio>
						<Monto>4845.97</Monto>
						<Descripcion>EFECTIVO</Descripcion>
						<Tipo>PAGOS_EFECTIVO</Tipo>
						<Cuotas>0</Cuotas>
						<Desglose>
							<Monto>4845.97</Monto>
						</Desglose>
					</Pago>
					<Pago>
						<Orden>11</Orden>
						<EsCambio>Sí</EsCambio>
						<Monto>0</Monto>
						<Tipo>PAGOS_OTROS</Tipo>
						<Cuotas>0</Cuotas>
						<Desglose>
							<Monto>0</Monto>
						</Desglose>
					</Pago>
					<Cierre>
						<Orden>12</Orden>
						<TipoDocumento>DocumentoFiscal</TipoDocumento>
						<SubTipoDocumento>Factura</SubTipoDocumento>
						<CalificadorDocumento>B</CalificadorDocumento>
						<Estacion>Ticket</Estacion>
						<Registro>HSHSAB0000009658</Registro>
						<Version>01.00</Version>
						<NumeroDocumento>54745</NumeroDocumento>
						<NumeroCompleto>00011-00054745</NumeroCompleto>
						<Totales>
							<Total>4845.97</Total>
							<TotalBase>4385.49</TotalBase>
							<TotalNoGravado>0</TotalNoGravado>
							<TotalGravado>4385.49</TotalGravado>
							<TotalExento>0</TotalExento>
							<TotalIVA>460.48</TotalIVA>
							<TotalII>0</TotalII>
							<TotalOtrosTributos>0</TotalOtrosTributos>
							<TotalPagos>4845.97</TotalPagos>
							<OperacionesVenta>1</OperacionesVenta>
							<DiscriminacionIVA type="list">
								<IVA>
									<TasaIVA>10.5</TasaIVA>
									<ImpIntFijo>0</ImpIntFijo>
									<ImpIntVariable>0</ImpIntVariable>
									<NetoSinIVA>4385.49</NetoSinIVA>
									<MontoIVA>460.48</MontoIVA>
								</IVA>
							</DiscriminacionIVA>
							<DiscriminacionOtrosTributos type="list">
							</DiscriminacionOtrosTributos>
						</Totales>
					</Cierre>
				</Items>
			</Documento>
			<Documento>
				<Orden>1</Orden>
				<Items type="list">
					<Cliente>
						<Orden>0</Orden>
						<NroDocumento>1</NroDocumento>
						<NroSecuencia>1</NroSecuencia>
						<TipoDocumento>DNI</TipoDocumento>
						<TipoCliente>ClienteConsumidorFinal</TipoCliente>
						<Nombre>CONSUMIDOR FINAL</Nombre>
						<Direccion>.</Direccion>
					</Cliente>
					<AtributosImpresion>
						<Orden>1</Orden>
						<Personalidad>ImpresorFiscal</Personalidad>
						<Producto>SMH/PT-250F 6.02A</Producto>
						<Modelo>Hasar SMH/PT-250F 1.</Modelo>
						<ModeloImpresor>80250-64</ModeloImpresor>
						<Estacion>Ticket</Estacion>
						<AnchoPapel>64</AnchoPapel>
						<AltoPapel>0</AltoPapel>
						<TipoHojaAlto>AltoA4</TipoHojaAlto>
						<TipoHojaAncho>AnchoNormal</TipoHojaAncho>
						<ImprimeLeyendasOpcionales>Sí</ImprimeLeyendasOpcionales>
						<ImprimeCodigos>NoImprimeCodigos</ImprimeCodigos>
						<ImprimeUnidadesMedida>No</ImprimeUnidadesMedida>
						<ImprimeMarcos>No</ImprimeMarcos>
						<ModoEntrenamiento>No</ModoEntrenamiento>
						<SignoMonetario>$</SignoMonetario>
						<UsarColorAlternativo>No</UsarColorAlternativo>
						<ColorAlternativo>Negro</ColorAlternativo>
						<ImprimeQR>Sí</ImprimeQR>
						<TipoInterlineado>InterlineadoNormal</TipoInterlineado>
					</AtributosImpresion>
					<Emisor>
						<Orden>2</Orden>
						<CUIT>20347825604</CUIT>
						<RazonSocial>COLANERI SERGIO ALEJANDRO</RazonSocial>
						<NroRegistro>HSHSAB0000009658</NroRegistro>
						<FechaInicioActividades>20180901</FechaInicioActividades>
						<IngBrutos>20-34782560-4</IngBrutos>
						<TipoEmisor>EmisorInscripto</TipoEmisor>
						<TipoHabilitacion>ComprobantesA</TipoHabilitacion>
						<LimiteM>1000</LimiteM>
					</Emisor>
					<LineaUsuario>
						<Orden>3</Orden>
						<Estacion>Ticket</Estacion>
						<Tipo>OwnerAddress</Tipo>
						<Linea>1</Linea>
						<Texto>
							<Texto>CALLE 16 ESQ 19</Texto>
							<Atributos type="list">
							</Atributos>
						</Texto>
					</LineaUsuario>
					<LineaUsuario>
						<Orden>4</Orden>
						<Estacion>Ticket</Estacion>
						<Tipo>OwnerAddress</Tipo>
						<Linea>2</Linea>
						<Texto>
							<Texto>C.P.(3700)-PCIA. R. S. PEÑA-CHACO</Texto>
							<Atributos type="list">
							</Atributos>
						</Texto>
					</LineaUsuario>
					<LineaUsuario>
						<Orden>5</Orden>
						<Estacion>Ticket</Estacion>
						<Tipo>Fantasy</Tipo>
						<Linea>1</Linea>
						<Texto>
							<Texto>ÑANDEJARA CARNES</Texto>
							<Atributos type="list">
							</Atributos>
						</Texto>
					</LineaUsuario>
					<Apertura>
						<Orden>6</Orden>
						<TipoDocumento>DocumentoFiscal</TipoDocumento>
						<SubTipoDocumento>Factura</SubTipoDocumento>
						<CalificadorDocumento>B</CalificadorDocumento>
						<Estacion>Ticket</Estacion>
						<TipoAFIP>82</TipoAFIP>
						<POS>00011</POS>
						<Fecha>230130</Fecha>
						<Hora>180917</Hora>
						<NumeroDocumento>54746</NumeroDocumento>
						<NumeroCompleto>00011-00054746</NumeroCompleto>
						<IdentificadorCopia>Original</IdentificadorCopia>
					</Apertura>
					<Venta>
						<Orden>7</Orden>
						<Descripcion>MOLIDA ESPECIAL TERNERA</Descripcion>
						<CodigoInterno>00043</CodigoInterno>
						<CodigoMatrix>00043</CodigoMatrix>
						<Cantidad>2.02</Cantidad>
						<UnidadesMatrix>0</UnidadesMatrix>
						<UnidadMedida>UM_KILO</UnidadMedida>
						<Precio>1495.549</Precio>
						<CondicionIVA>CondicionIVAGravado</CondicionIVA>
						<TasaIVA>10.5</TasaIVA>
						<ImpuestoComoCoeficiente>Sí</ImpuestoComoCoeficiente>
						<ImpInt>0</ImpInt>
						<ImpIntFijo>No</ImpIntFijo>
						<PorBaseImponible>No</PorBaseImponible>
						<Desglose>
							<Cantidad>2.02</Cantidad>
							<PrecioFinal>1495.549</PrecioFinal>
							<MontoFinal>3021.01</MontoFinal>
							<TasaIVA>10.5</TasaIVA>
							<PrecioBase>1353.438</PrecioBase>
							<MontoTotalBase>2733.95</MontoTotalBase>
							<MontoTotalIVA>287.06</MontoTotalIVA>
							<MontoTotalII>0</MontoTotalII>
							<ImpIntFijo>No</ImpIntFijo>
							<ConceptosNoGravados>0</ConceptosNoGravados>
							<K>0</K>
						</Desglose>
					</Venta>
					<Venta>
						<Orden>8</Orden>
						<Descripcion>PECETO DE TERNERA</Descripcion>
						<CodigoInterno>00231</CodigoInterno>
						<CodigoMatrix>00231</CodigoMatrix>
						<Cantidad>1.16</Cantidad>
						<UnidadesMatrix>0</UnidadesMatrix>
						<UnidadMedida>UM_KILO</UnidadMedida>
						<Precio>1656.742</Precio>
						<CondicionIVA>CondicionIVAGravado</CondicionIVA>
						<TasaIVA>10.5</TasaIVA>
						<ImpuestoComoCoeficiente>Sí</ImpuestoComoCoeficiente>
						<ImpInt>0</ImpInt>
						<ImpIntFijo>No</ImpIntFijo>
						<PorBaseImponible>No</PorBaseImponible>
						<Desglose>
							<Cantidad>1.16</Cantidad>
							<PrecioFinal>1656.742</PrecioFinal>
							<MontoFinal>1921.82</MontoFinal>
							<TasaIVA>10.5</TasaIVA>
							<PrecioBase>1499.314</PrecioBase>
							<MontoTotalBase>1739.2</MontoTotalBase>
							<MontoTotalIVA>182.62</MontoTotalIVA>
							<MontoTotalII>0</MontoTotalII>
							<ImpIntFijo>No</ImpIntFijo>
							<ConceptosNoGravados>0</ConceptosNoGravados>
							<K>0</K>
						</Desglose>
					</Venta>
					<DiscriminacionIVA>
						<Orden>9</Orden>
						<CondicionIVA>CondicionIVAGravado</CondicionIVA>
						<TasaIVA>10.5</TasaIVA>
						<Base>4473.15</Base>
						<MontoIVA>469.68</MontoIVA>
					</DiscriminacionIVA>
					<Totales>
						<Orden>10</Orden>
						<Base>4473.15</Base>
						<MontoIVA>469.68</MontoIVA>
						<MontoII>0</MontoII>
						<MontoOtrosTributos>0</MontoOtrosTributos>
						<MontoNoGravado>0</MontoNoGravado>
						<MontoExento>0</MontoExento>
						<MontoGravado>4473.15</MontoGravado>
						<AjusteRedondeo>0</AjusteRedondeo>
						<Final>4942.83</Final>
						<ImpresionBase>4473.14</ImpresionBase>
						<ImpresionMontoIVA>469.68</ImpresionMontoIVA>
						<ImpresionMontoII>0</ImpresionMontoII>
						<ImpresionFinal>4942.83</ImpresionFinal>
						<TipoTotales>TotalesAlFinal</TipoTotales>
					</Totales>
					<Pago>
						<Orden>11</Orden>
						<EsCambio>No</EsCambio>
						<Monto>4942.83</Monto>
						<Descripcion>EFECTIVO</Descripcion>
						<Tipo>PAGOS_EFECTIVO</Tipo>
						<Cuotas>0</Cuotas>
						<Desglose>
							<Monto>4942.83</Monto>
						</Desglose>
					</Pago>
					<Pago>
						<Orden>12</Orden>
						<EsCambio>Sí</EsCambio>
						<Monto>0</Monto>
						<Tipo>PAGOS_OTROS</Tipo>
						<Cuotas>0</Cuotas>
						<Desglose>
							<Monto>0</Monto>
						</Desglose>
					</Pago>
					<Cierre>
						<Orden>13</Orden>
						<TipoDocumento>DocumentoFiscal</TipoDocumento>
						<SubTipoDocumento>Factura</SubTipoDocumento>
						<CalificadorDocumento>B</CalificadorDocumento>
						<Estacion>Ticket</Estacion>
						<Registro>HSHSAB0000009658</Registro>
						<Version>01.00</Version>
						<NumeroDocumento>54746</NumeroDocumento>
						<NumeroCompleto>00011-00054746</NumeroCompleto>
						<Totales>
							<Total>4942.83</Total>
							<TotalBase>4473.15</TotalBase>
							<TotalNoGravado>0</TotalNoGravado>
							<TotalGravado>4473.15</TotalGravado>
							<TotalExento>0</TotalExento>
							<TotalIVA>469.68</TotalIVA>
							<TotalII>0</TotalII>
							<TotalOtrosTributos>0</TotalOtrosTributos>
							<TotalPagos>4942.83</TotalPagos>
							<OperacionesVenta>2</OperacionesVenta>
							<DiscriminacionIVA type="list">
								<IVA>
									<TasaIVA>10.5</TasaIVA>
									<ImpIntFijo>0</ImpIntFijo>
									<ImpIntVariable>0</ImpIntVariable>
									<NetoSinIVA>4473.15</NetoSinIVA>
									<MontoIVA>469.68</MontoIVA>
								</IVA>
							</DiscriminacionIVA>
							<DiscriminacionOtrosTributos type="list">
							</DiscriminacionOtrosTributos>
						</Totales>
					</Cierre>
				</Items>
			</Documento>
			<Documento>
				<Orden>2</Orden>
				<Items type="list">
					<Cliente>
						<Orden>0</Orden>
						<NroDocumento>1</NroDocumento>
						<NroSecuencia>1</NroSecuencia>
						<TipoDocumento>DNI</TipoDocumento>
						<TipoCliente>ClienteConsumidorFinal</TipoCliente>
						<Nombre>CONSUMIDOR FINAL</Nombre>
						<Direccion>.</Direccion>
					</Cliente>
					<AtributosImpresion>
						<Orden>1</Orden>
						<Personalidad>ImpresorFiscal</Personalidad>
						<Producto>SMH/PT-250F 6.02A</Producto>
						<Modelo>Hasar SMH/PT-250F 1.</Modelo>
						<ModeloImpresor>80250-64</ModeloImpresor>
						<Estacion>Ticket</Estacion>
						<AnchoPapel>64</AnchoPapel>
						<AltoPapel>0</AltoPapel>
						<TipoHojaAlto>AltoA4</TipoHojaAlto>
						<TipoHojaAncho>AnchoNormal</TipoHojaAncho>
						<ImprimeLeyendasOpcionales>Sí</ImprimeLeyendasOpcionales>
						<ImprimeCodigos>NoImprimeCodigos</ImprimeCodigos>
						<ImprimeUnidadesMedida>No</ImprimeUnidadesMedida>
						<ImprimeMarcos>No</ImprimeMarcos>
						<ModoEntrenamiento>No</ModoEntrenamiento>
						<SignoMonetario>$</SignoMonetario>
						<UsarColorAlternativo>No</UsarColorAlternativo>
						<ColorAlternativo>Negro</ColorAlternativo>
						<ImprimeQR>Sí</ImprimeQR>
						<TipoInterlineado>InterlineadoNormal</TipoInterlineado>
					</AtributosImpresion>
					<Emisor>
						<Orden>2</Orden>
						<CUIT>20347825604</CUIT>
						<RazonSocial>COLANERI SERGIO ALEJANDRO</RazonSocial>
						<NroRegistro>HSHSAB0000009658</NroRegistro>
						<FechaInicioActividades>20180901</FechaInicioActividades>
						<IngBrutos>20-34782560-4</IngBrutos>
						<TipoEmisor>EmisorInscripto</TipoEmisor>
						<TipoHabilitacion>ComprobantesA</TipoHabilitacion>
						<LimiteM>1000</LimiteM>
					</Emisor>
					<LineaUsuario>
						<Orden>3</Orden>
						<Estacion>Ticket</Estacion>
						<Tipo>OwnerAddress</Tipo>
						<Linea>1</Linea>
						<Texto>
							<Texto>CALLE 16 ESQ 19</Texto>
							<Atributos type="list">
							</Atributos>
						</Texto>
					</LineaUsuario>
					<LineaUsuario>
						<Orden>4</Orden>
						<Estacion>Ticket</Estacion>
						<Tipo>OwnerAddress</Tipo>
						<Linea>2</Linea>
						<Texto>
							<Texto>C.P.(3700)-PCIA. R. S. PEÑA-CHACO</Texto>
							<Atributos type="list">
							</Atributos>
						</Texto>
					</LineaUsuario>
					<LineaUsuario>
						<Orden>5</Orden>
						<Estacion>Ticket</Estacion>
						<Tipo>Fantasy</Tipo>
						<Linea>1</Linea>
						<Texto>
							<Texto>ÑANDEJARA CARNES</Texto>
							<Atributos type="list">
							</Atributos>
						</Texto>
					</LineaUsuario>
					<Apertura>
						<Orden>6</Orden>
						<TipoDocumento>DocumentoFiscal</TipoDocumento>
						<SubTipoDocumento>Factura</SubTipoDocumento>
						<CalificadorDocumento>B</CalificadorDocumento>
						<Estacion>Ticket</Estacion>
						<TipoAFIP>82</TipoAFIP>
						<POS>00011</POS>
						<Fecha>230130</Fecha>
						<Hora>181207</Hora>
						<NumeroDocumento>54747</NumeroDocumento>
						<NumeroCompleto>00011-00054747</NumeroCompleto>
						<IdentificadorCopia>Original</IdentificadorCopia>
					</Apertura>
					<Venta>
						<Orden>7</Orden>
						<Descripcion>COSTELETA DE TERNERA</Descripcion>
						<CodigoInterno>00224</CodigoInterno>
						<CodigoMatrix>00224</CodigoMatrix>
						<Cantidad>2.62</Cantidad>
						<UnidadesMatrix>0</UnidadesMatrix>
						<UnidadMedida>UM_KILO</UnidadMedida>
						<Precio>1318.471</Precio>
						<CondicionIVA>CondicionIVAGravado</CondicionIVA>
						<TasaIVA>10.5</TasaIVA>
						<ImpuestoComoCoeficiente>Sí</ImpuestoComoCoeficiente>
						<ImpInt>0</ImpInt>
						<ImpIntFijo>No</ImpIntFijo>
						<PorBaseImponible>No</PorBaseImponible>
						<Desglose>
							<Cantidad>2.62</Cantidad>
							<PrecioFinal>1318.471</PrecioFinal>
							<MontoFinal>3454.39</MontoFinal>
							<TasaIVA>10.5</TasaIVA>
							<PrecioBase>1193.1864</PrecioBase>
							<MontoTotalBase>3126.14</MontoTotalBase>
							<MontoTotalIVA>328.25</MontoTotalIVA>
							<MontoTotalII>0</MontoTotalII>
							<ImpIntFijo>No</ImpIntFijo>
							<ConceptosNoGravados>0</ConceptosNoGravados>
							<K>0</K>
						</Desglose>
					</Venta>
					<DiscriminacionIVA>
						<Orden>8</Orden>
						<CondicionIVA>CondicionIVAGravado</CondicionIVA>
						<TasaIVA>10.5</TasaIVA>
						<Base>3126.14</Base>
						<MontoIVA>328.25</MontoIVA>
					</DiscriminacionIVA>
					<Totales>
						<Orden>9</Orden>
						<Base>3126.14</Base>
						<MontoIVA>328.25</MontoIVA>
						<MontoII>0</MontoII>
						<MontoOtrosTributos>0</MontoOtrosTributos>
						<MontoNoGravado>0</MontoNoGravado>
						<MontoExento>0</MontoExento>
						<MontoGravado>3126.14</MontoGravado>
						<AjusteRedondeo>0</AjusteRedondeo>
						<Final>3454.39</Final>
						<ImpresionBase>3126.15</ImpresionBase>
						<ImpresionMontoIVA>328.25</ImpresionMontoIVA>
						<ImpresionMontoII>0</ImpresionMontoII>
						<ImpresionFinal>3454.39</ImpresionFinal>
						<TipoTotales>TotalesAlFinal</TipoTotales>
					</Totales>
					<Pago>
						<Orden>10</Orden>
						<EsCambio>No</EsCambio>
						<Monto>3454.39</Monto>
						<Descripcion>EFECTIVO</Descripcion>
						<Tipo>PAGOS_EFECTIVO</Tipo>
						<Cuotas>0</Cuotas>
						<Desglose>
							<Monto>3454.39</Monto>
						</Desglose>
					</Pago>
					<Pago>
						<Orden>11</Orden>
						<EsCambio>Sí</EsCambio>
						<Monto>0</Monto>
						<Tipo>PAGOS_OTROS</Tipo>
						<Cuotas>0</Cuotas>
						<Desglose>
							<Monto>0</Monto>
						</Desglose>
					</Pago>
					<Cierre>
						<Orden>12</Orden>
						<TipoDocumento>DocumentoFiscal</TipoDocumento>
						<SubTipoDocumento>Factura</SubTipoDocumento>
						<CalificadorDocumento>B</CalificadorDocumento>
						<Estacion>Ticket</Estacion>
						<Registro>HSHSAB0000009658</Registro>
						<Version>01.00</Version>
						<NumeroDocumento>54747</NumeroDocumento>
						<NumeroCompleto>00011-00054747</NumeroCompleto>
						<Totales>
							<Total>3454.39</Total>
							<TotalBase>3126.14</TotalBase>
							<TotalNoGravado>0</TotalNoGravado>
							<TotalGravado>3126.14</TotalGravado>
							<TotalExento>0</TotalExento>
							<TotalIVA>328.25</TotalIVA>
							<TotalII>0</TotalII>
							<TotalOtrosTributos>0</TotalOtrosTributos>
							<TotalPagos>3454.39</TotalPagos>
							<OperacionesVenta>1</OperacionesVenta>
							<DiscriminacionIVA type="list">
								<IVA>
									<TasaIVA>10.5</TasaIVA>
									<ImpIntFijo>0</ImpIntFijo>
									<ImpIntVariable>0</ImpIntVariable>
									<NetoSinIVA>3126.14</NetoSinIVA>
									<MontoIVA>328.25</MontoIVA>
								</IVA>
							</DiscriminacionIVA>
							<DiscriminacionOtrosTributos type="list">
							</DiscriminacionOtrosTributos>
						</Totales>
					</Cierre>
				</Items>
			</Documento>
			<Documento>
				<Orden>3</Orden>
				<Items type="list">
					<Cliente>
						<Orden>0</Orden>
						<NroDocumento>1</NroDocumento>
						<NroSecuencia>1</NroSecuencia>
						<TipoDocumento>DNI</TipoDocumento>
						<TipoCliente>ClienteConsumidorFinal</TipoCliente>
						<Nombre>CONSUMIDOR FINAL</Nombre>
						<Direccion>.</Direccion>
					</Cliente>
					<AtributosImpresion>
						<Orden>1</Orden>
						<Personalidad>ImpresorFiscal</Personalidad>
						<Producto>SMH/PT-250F 6.02A</Producto>
						<Modelo>Hasar SMH/PT-250F 1.</Modelo>
						<ModeloImpresor>80250-64</ModeloImpresor>
						<Estacion>Ticket</Estacion>
						<AnchoPapel>64</AnchoPapel>
						<AltoPapel>0</AltoPapel>
						<TipoHojaAlto>AltoA4</TipoHojaAlto>
						<TipoHojaAncho>AnchoNormal</TipoHojaAncho>
						<ImprimeLeyendasOpcionales>Sí</ImprimeLeyendasOpcionales>
						<ImprimeCodigos>NoImprimeCodigos</ImprimeCodigos>
						<ImprimeUnidadesMedida>No</ImprimeUnidadesMedida>
						<ImprimeMarcos>No</ImprimeMarcos>
						<ModoEntrenamiento>No</ModoEntrenamiento>
						<SignoMonetario>$</SignoMonetario>
						<UsarColorAlternativo>No</UsarColorAlternativo>
						<ColorAlternativo>Negro</ColorAlternativo>
						<ImprimeQR>Sí</ImprimeQR>
						<TipoInterlineado>InterlineadoNormal</TipoInterlineado>
					</AtributosImpresion>
					<Emisor>
						<Orden>2</Orden>
						<CUIT>20347825604</CUIT>
						<RazonSocial>COLANERI SERGIO ALEJANDRO</RazonSocial>
						<NroRegistro>HSHSAB0000009658</NroRegistro>
						<FechaInicioActividades>20180901</FechaInicioActividades>
						<IngBrutos>20-34782560-4</IngBrutos>
						<TipoEmisor>EmisorInscripto</TipoEmisor>
						<TipoHabilitacion>ComprobantesA</TipoHabilitacion>
						<LimiteM>1000</LimiteM>
					</Emisor>
					<LineaUsuario>
						<Orden>3</Orden>
						<Estacion>Ticket</Estacion>
						<Tipo>OwnerAddress</Tipo>
						<Linea>1</Linea>
						<Texto>
							<Texto>CALLE 16 ESQ 19</Texto>
							<Atributos type="list">
							</Atributos>
						</Texto>
					</LineaUsuario>
					<LineaUsuario>
						<Orden>4</Orden>
						<Estacion>Ticket</Estacion>
						<Tipo>OwnerAddress</Tipo>
						<Linea>2</Linea>
						<Texto>
							<Texto>C.P.(3700)-PCIA. R. S. PEÑA-CHACO</Texto>
							<Atributos type="list">
							</Atributos>
						</Texto>
					</LineaUsuario>
					<LineaUsuario>
						<Orden>5</Orden>
						<Estacion>Ticket</Estacion>
						<Tipo>Fantasy</Tipo>
						<Linea>1</Linea>
						<Texto>
							<Texto>ÑANDEJARA CARNES</Texto>
							<Atributos type="list">
							</Atributos>
						</Texto>
					</LineaUsuario>
					<Apertura>
						<Orden>6</Orden>
						<TipoDocumento>DocumentoFiscal</TipoDocumento>
						<SubTipoDocumento>Factura</SubTipoDocumento>
						<CalificadorDocumento>B</CalificadorDocumento>
						<Estacion>Ticket</Estacion>
						<TipoAFIP>82</TipoAFIP>
						<POS>00011</POS>
						<Fecha>230130</Fecha>
						<Hora>181955</Hora>
						<NumeroDocumento>54748</NumeroDocumento>
						<NumeroCompleto>00011-00054748</NumeroCompleto>
						<IdentificadorCopia>Original</IdentificadorCopia>
					</Apertura>
					<Venta>
						<Orden>7</Orden>
						<Descripcion>MARUCHA DE TERNERA</Descripcion>
						<CodigoInterno>00044</CodigoInterno>
						<CodigoMatrix>00044</CodigoMatrix>
						<Cantidad>3.025</Cantidad>
						<UnidadesMatrix>0</UnidadesMatrix>
						<UnidadMedida>UM_KILO</UnidadMedida>
						<Precio>849</Precio>
						<CondicionIVA>CondicionIVAGravado</CondicionIVA>
						<TasaIVA>10.5</TasaIVA>
						<ImpuestoComoCoeficiente>Sí</ImpuestoComoCoeficiente>
						<ImpInt>0</ImpInt>
						<ImpIntFijo>No</ImpIntFijo>
						<PorBaseImponible>No</PorBaseImponible>
						<Desglose>
							<Cantidad>3.025</Cantidad>
							<PrecioFinal>849</PrecioFinal>
							<MontoFinal>2568.23</MontoFinal>
							<TasaIVA>10.5</TasaIVA>
							<PrecioBase>768.3258</PrecioBase>
							<MontoTotalBase>2324.19</MontoTotalBase>
							<MontoTotalIVA>244.04</MontoTotalIVA>
							<MontoTotalII>0</MontoTotalII>
							<ImpIntFijo>No</ImpIntFijo>
							<ConceptosNoGravados>0</ConceptosNoGravados>
							<K>0</K>
						</Desglose>
					</Venta>
					<DiscriminacionIVA>
						<Orden>8</Orden>
						<CondicionIVA>CondicionIVAGravado</CondicionIVA>
						<TasaIVA>10.5</TasaIVA>
						<Base>2324.19</Base>
						<MontoIVA>244.04</MontoIVA>
					</DiscriminacionIVA>
					<Totales>
						<Orden>9</Orden>
						<Base>2324.19</Base>
						<MontoIVA>244.04</MontoIVA>
						<MontoII>0</MontoII>
						<MontoOtrosTributos>0</MontoOtrosTributos>
						<MontoNoGravado>0</MontoNoGravado>
						<MontoExento>0</MontoExento>
						<MontoGravado>2324.19</MontoGravado>
						<AjusteRedondeo>0</AjusteRedondeo>
						<Final>2568.23</Final>
						<ImpresionBase>2324.19</ImpresionBase>
						<ImpresionMontoIVA>244.04</ImpresionMontoIVA>
						<ImpresionMontoII>0</ImpresionMontoII>
						<ImpresionFinal>2568.23</ImpresionFinal>
						<TipoTotales>TotalesAlFinal</TipoTotales>
					</Totales>
					<Pago>
						<Orden>10</Orden>
						<EsCambio>No</EsCambio>
						<Monto>2568.22</Monto>
						<Descripcion>EFECTIVO</Descripcion>
						<Tipo>PAGOS_EFECTIVO</Tipo>
						<Cuotas>0</Cuotas>
						<Desglose>
							<Monto>2568.22</Monto>
						</Desglose>
					</Pago>
					<Pago>
						<Orden>11</Orden>
						<EsCambio>No</EsCambio>
						<Monto>0.01</Monto>
						<Descripcion>Saldo</Descripcion>
						<Tipo>PAGOS_SALDO</Tipo>
						<Cuotas>0</Cuotas>
						<Desglose>
							<Monto>0.01</Monto>
						</Desglose>
					</Pago>
					<Cierre>
						<Orden>12</Orden>
						<TipoDocumento>DocumentoFiscal</TipoDocumento>
						<SubTipoDocumento>Factura</SubTipoDocumento>
						<CalificadorDocumento>B</CalificadorDocumento>
						<Estacion>Ticket</Estacion>
						<Registro>HSHSAB0000009658</Registro>
						<Version>01.00</Version>
						<NumeroDocumento>54748</NumeroDocumento>
						<NumeroCompleto>00011-00054748</NumeroCompleto>
						<Totales>
							<Total>2568.23</Total>
							<TotalBase>2324.19</TotalBase>
							<TotalNoGravado>0</TotalNoGravado>
							<TotalGravado>2324.19</TotalGravado>
							<TotalExento>0</TotalExento>
							<TotalIVA>244.04</TotalIVA>
							<TotalII>0</TotalII>
							<TotalOtrosTributos>0</TotalOtrosTributos>
							<TotalPagos>2568.23</TotalPagos>
							<OperacionesVenta>1</OperacionesVenta>
							<DiscriminacionIVA type="list">
								<IVA>
									<TasaIVA>10.5</TasaIVA>
									<ImpIntFijo>0</ImpIntFijo>
									<ImpIntVariable>0</ImpIntVariable>
									<NetoSinIVA>2324.19</NetoSinIVA>
									<MontoIVA>244.04</MontoIVA>
								</IVA>
							</DiscriminacionIVA>
							<DiscriminacionOtrosTributos type="list">
							</DiscriminacionOtrosTributos>
						</Totales>
					</Cierre>
				</Items>
			</Documento>
			<Documento>
				<Orden>4</Orden>
				<Items type="list">
					<Cliente>
						<Orden>0</Orden>
						<NroDocumento>1</NroDocumento>
						<NroSecuencia>1</NroSecuencia>
						<TipoDocumento>DNI</TipoDocumento>
						<TipoCliente>ClienteConsumidorFinal</TipoCliente>
						<Nombre>CONSUMIDOR FINAL</Nombre>
						<Direccion>.</Direccion>
					</Cliente>
					<AtributosImpresion>
						<Orden>1</Orden>
						<Personalidad>ImpresorFiscal</Personalidad>
						<Producto>SMH/PT-250F 6.02A</Producto>
						<Modelo>Hasar SMH/PT-250F 1.</Modelo>
						<ModeloImpresor>80250-64</ModeloImpresor>
						<Estacion>Ticket</Estacion>
						<AnchoPapel>64</AnchoPapel>
						<AltoPapel>0</AltoPapel>
						<TipoHojaAlto>AltoA4</TipoHojaAlto>
						<TipoHojaAncho>AnchoNormal</TipoHojaAncho>
						<ImprimeLeyendasOpcionales>Sí</ImprimeLeyendasOpcionales>
						<ImprimeCodigos>NoImprimeCodigos</ImprimeCodigos>
						<ImprimeUnidadesMedida>No</ImprimeUnidadesMedida>
						<ImprimeMarcos>No</ImprimeMarcos>
						<ModoEntrenamiento>No</ModoEntrenamiento>
						<SignoMonetario>$</SignoMonetario>
						<UsarColorAlternativo>No</UsarColorAlternativo>
						<ColorAlternativo>Negro</ColorAlternativo>
						<ImprimeQR>Sí</ImprimeQR>
						<TipoInterlineado>InterlineadoNormal</TipoInterlineado>
					</AtributosImpresion>
					<Emisor>
						<Orden>2</Orden>
						<CUIT>20347825604</CUIT>
						<RazonSocial>COLANERI SERGIO ALEJANDRO</RazonSocial>
						<NroRegistro>HSHSAB0000009658</NroRegistro>
						<FechaInicioActividades>20180901</FechaInicioActividades>
						<IngBrutos>20-34782560-4</IngBrutos>
						<TipoEmisor>EmisorInscripto</TipoEmisor>
						<TipoHabilitacion>ComprobantesA</TipoHabilitacion>
						<LimiteM>1000</LimiteM>
					</Emisor>
					<LineaUsuario>
						<Orden>3</Orden>
						<Estacion>Ticket</Estacion>
						<Tipo>OwnerAddress</Tipo>
						<Linea>1</Linea>
						<Texto>
							<Texto>CALLE 16 ESQ 19</Texto>
							<Atributos type="list">
							</Atributos>
						</Texto>
					</LineaUsuario>
					<LineaUsuario>
						<Orden>4</Orden>
						<Estacion>Ticket</Estacion>
						<Tipo>OwnerAddress</Tipo>
						<Linea>2</Linea>
						<Texto>
							<Texto>C.P.(3700)-PCIA. R. S. PEÑA-CHACO</Texto>
							<Atributos type="list">
							</Atributos>
						</Texto>
					</LineaUsuario>
					<LineaUsuario>
						<Orden>5</Orden>
						<Estacion>Ticket</Estacion>
						<Tipo>Fantasy</Tipo>
						<Linea>1</Linea>
						<Texto>
							<Texto>ÑANDEJARA CARNES</Texto>
							<Atributos type="list">
							</Atributos>
						</Texto>
					</LineaUsuario>
					<Apertura>
						<Orden>6</Orden>
						<TipoDocumento>DocumentoFiscal</TipoDocumento>
						<SubTipoDocumento>Factura</SubTipoDocumento>
						<CalificadorDocumento>B</CalificadorDocumento>
						<Estacion>Ticket</Estacion>
						<TipoAFIP>82</TipoAFIP>
						<POS>00011</POS>
						<Fecha>230130</Fecha>
						<Hora>182558</Hora>
						<NumeroDocumento>54749</NumeroDocumento>
						<NumeroCompleto>00011-00054749</NumeroCompleto>
						<IdentificadorCopia>Original</IdentificadorCopia>
					</Apertura>
					<Venta>
						<Orden>7</Orden>
						<Descripcion>VACIO DE TERNERA</Descripcion>
						<CodigoInterno>00235</CodigoInterno>
						<CodigoMatrix>00235</CodigoMatrix>
						<Cantidad>1.52</Cantidad>
						<UnidadesMatrix>0</UnidadesMatrix>
						<UnidadMedida>UM_KILO</UnidadMedida>
						<Precio>1695</Precio>
						<CondicionIVA>CondicionIVAGravado</CondicionIVA>
						<TasaIVA>10.5</TasaIVA>
						<ImpuestoComoCoeficiente>Sí</ImpuestoComoCoeficiente>
						<ImpInt>0</ImpInt>
						<ImpIntFijo>No</ImpIntFijo>
						<PorBaseImponible>No</PorBaseImponible>
						<Desglose>
							<Cantidad>1.52</Cantidad>
							<PrecioFinal>1695</PrecioFinal>
							<MontoFinal>2576.4</MontoFinal>
							<TasaIVA>10.5</TasaIVA>
							<PrecioBase>1533.9367</PrecioBase>
							<MontoTotalBase>2331.58</MontoTotalBase>
							<MontoTotalIVA>244.82</MontoTotalIVA>
							<MontoTotalII>0</MontoTotalII>
							<ImpIntFijo>No</ImpIntFijo>
							<ConceptosNoGravados>0</ConceptosNoGravados>
							<K>0</K>
						</Desglose>
					</Venta>
					<Venta>
						<Orden>8</Orden>
						<Descripcion>CHORIZO 100% CERDO</Descripcion>
						<CodigoInterno>00068</CodigoInterno>
						<CodigoMatrix>00068</CodigoMatrix>
						<Cantidad>0.205</Cantidad>
						<UnidadesMatrix>0</UnidadesMatrix>
						<UnidadMedida>UM_KILO</UnidadMedida>
						<Precio>999</Precio>
						<CondicionIVA>CondicionIVAGravado</CondicionIVA>
						<TasaIVA>10.5</TasaIVA>
						<ImpuestoComoCoeficiente>Sí</ImpuestoComoCoeficiente>
						<ImpInt>0</ImpInt>
						<ImpIntFijo>No</ImpIntFijo>
						<PorBaseImponible>No</PorBaseImponible>
						<Desglose>
							<Cantidad>0.205</Cantidad>
							<PrecioFinal>999</PrecioFinal>
							<MontoFinal>204.8</MontoFinal>
							<TasaIVA>10.5</TasaIVA>
							<PrecioBase>904.0724</PrecioBase>
							<MontoTotalBase>185.34</MontoTotalBase>
							<MontoTotalIVA>19.46</MontoTotalIVA>
							<MontoTotalII>0</MontoTotalII>
							<ImpIntFijo>No</ImpIntFijo>
							<ConceptosNoGravados>0</ConceptosNoGravados>
							<K>0</K>
						</Desglose>
					</Venta>
					<Venta>
						<Orden>9</Orden>
						<Descripcion>SALCHICHA PARRILLERA</Descripcion>
						<CodigoInterno>00061</CodigoInterno>
						<CodigoMatrix>00061</CodigoMatrix>
						<Cantidad>0.175</Cantidad>
						<UnidadesMatrix>0</UnidadesMatrix>
						<UnidadMedida>UM_KILO</UnidadMedida>
						<Precio>1499</Precio>
						<CondicionIVA>CondicionIVAGravado</CondicionIVA>
						<TasaIVA>10.5</TasaIVA>
						<ImpuestoComoCoeficiente>Sí</ImpuestoComoCoeficiente>
						<ImpInt>0</ImpInt>
						<ImpIntFijo>No</ImpIntFijo>
						<PorBaseImponible>No</PorBaseImponible>
						<Desglose>
							<Cantidad>0.175</Cantidad>
							<PrecioFinal>1499</PrecioFinal>
							<MontoFinal>262.33</MontoFinal>
							<TasaIVA>10.5</TasaIVA>
							<PrecioBase>1356.5611</PrecioBase>
							<MontoTotalBase>237.4</MontoTotalBase>
							<MontoTotalIVA>24.93</MontoTotalIVA>
							<MontoTotalII>0</MontoTotalII>
							<ImpIntFijo>No</ImpIntFijo>
							<ConceptosNoGravados>0</ConceptosNoGravados>
							<K>0</K>
						</Desglose>
					</Venta>
					<DiscriminacionIVA>
						<Orden>10</Orden>
						<CondicionIVA>CondicionIVAGravado</CondicionIVA>
						<TasaIVA>10.5</TasaIVA>
						<Base>2754.32</Base>
						<MontoIVA>289.21</MontoIVA>
					</DiscriminacionIVA>
					<Totales>
						<Orden>11</Orden>
						<Base>2754.32</Base>
						<MontoIVA>289.21</MontoIVA>
						<MontoII>0</MontoII>
						<MontoOtrosTributos>0</MontoOtrosTributos>
						<MontoNoGravado>0</MontoNoGravado>
						<MontoExento>0</MontoExento>
						<MontoGravado>2754.32</MontoGravado>
						<AjusteRedondeo>0</AjusteRedondeo>
						<Final>3043.53</Final>
						<ImpresionBase>2754.31</ImpresionBase>
						<ImpresionMontoIVA>289.21</ImpresionMontoIVA>
						<ImpresionMontoII>0</ImpresionMontoII>
						<ImpresionFinal>3043.53</ImpresionFinal>
						<TipoTotales>TotalesAlFinal</TipoTotales>
					</Totales>
					<Pago>
						<Orden>12</Orden>
						<EsCambio>No</EsCambio>
						<Monto>3043.53</Monto>
						<Descripcion>EFECTIVO</Descripcion>
						<Tipo>PAGOS_EFECTIVO</Tipo>
						<Cuotas>0</Cuotas>
						<Desglose>
							<Monto>3043.53</Monto>
						</Desglose>
					</Pago>
					<Pago>
						<Orden>13</Orden>
						<EsCambio>Sí</EsCambio>
						<Monto>0</Monto>
						<Tipo>PAGOS_OTROS</Tipo>
						<Cuotas>0</Cuotas>
						<Desglose>
							<Monto>0</Monto>
						</Desglose>
					</Pago>
					<Cierre>
						<Orden>14</Orden>
						<TipoDocumento>DocumentoFiscal</TipoDocumento>
						<SubTipoDocumento>Factura</SubTipoDocumento>
						<CalificadorDocumento>B</CalificadorDocumento>
						<Estacion>Ticket</Estacion>
						<Registro>HSHSAB0000009658</Registro>
						<Version>01.00</Version>
						<NumeroDocumento>54749</NumeroDocumento>
						<NumeroCompleto>00011-00054749</NumeroCompleto>
						<Totales>
							<Total>3043.53</Total>
							<TotalBase>2754.32</TotalBase>
							<TotalNoGravado>0</TotalNoGravado>
							<TotalGravado>2754.32</TotalGravado>
							<TotalExento>0</TotalExento>
							<TotalIVA>289.21</TotalIVA>
							<TotalII>0</TotalII>
							<TotalOtrosTributos>0</TotalOtrosTributos>
							<TotalPagos>3043.53</TotalPagos>
							<OperacionesVenta>3</OperacionesVenta>
							<DiscriminacionIVA type="list">
								<IVA>
									<TasaIVA>10.5</TasaIVA>
									<ImpIntFijo>0</ImpIntFijo>
									<ImpIntVariable>0</ImpIntVariable>
									<NetoSinIVA>2754.32</NetoSinIVA>
									<MontoIVA>289.21</MontoIVA>
								</IVA>
							</DiscriminacionIVA>
							<DiscriminacionOtrosTributos type="list">
							</DiscriminacionOtrosTributos>
						</Totales>
					</Cierre>
				</Items>
			</Documento>
			<Documento>
				<Orden>5</Orden>
				<Items type="list">
					<Cliente>
						<Orden>0</Orden>
						<NroDocumento>1</NroDocumento>
						<NroSecuencia>1</NroSecuencia>
						<TipoDocumento>DNI</TipoDocumento>
						<TipoCliente>ClienteConsumidorFinal</TipoCliente>
						<Nombre>CONSUMIDOR FINAL</Nombre>
						<Direccion>.</Direccion>
					</Cliente>
					<AtributosImpresion>
						<Orden>1</Orden>
						<Personalidad>ImpresorFiscal</Personalidad>
						<Producto>SMH/PT-250F 6.02A</Producto>
						<Modelo>Hasar SMH/PT-250F 1.</Modelo>
						<ModeloImpresor>80250-64</ModeloImpresor>
						<Estacion>Ticket</Estacion>
						<AnchoPapel>64</AnchoPapel>
						<AltoPapel>0</AltoPapel>
						<TipoHojaAlto>AltoA4</TipoHojaAlto>
						<TipoHojaAncho>AnchoNormal</TipoHojaAncho>
						<ImprimeLeyendasOpcionales>Sí</ImprimeLeyendasOpcionales>
						<ImprimeCodigos>NoImprimeCodigos</ImprimeCodigos>
						<ImprimeUnidadesMedida>No</ImprimeUnidadesMedida>
						<ImprimeMarcos>No</ImprimeMarcos>
						<ModoEntrenamiento>No</ModoEntrenamiento>
						<SignoMonetario>$</SignoMonetario>
						<UsarColorAlternativo>No</UsarColorAlternativo>
						<ColorAlternativo>Negro</ColorAlternativo>
						<ImprimeQR>Sí</ImprimeQR>
						<TipoInterlineado>InterlineadoNormal</TipoInterlineado>
					</AtributosImpresion>
					<Emisor>
						<Orden>2</Orden>
						<CUIT>20347825604</CUIT>
						<RazonSocial>COLANERI SERGIO ALEJANDRO</RazonSocial>
						<NroRegistro>HSHSAB0000009658</NroRegistro>
						<FechaInicioActividades>20180901</FechaInicioActividades>
						<IngBrutos>20-34782560-4</IngBrutos>
						<TipoEmisor>EmisorInscripto</TipoEmisor>
						<TipoHabilitacion>ComprobantesA</TipoHabilitacion>
						<LimiteM>1000</LimiteM>
					</Emisor>
					<LineaUsuario>
						<Orden>3</Orden>
						<Estacion>Ticket</Estacion>
						<Tipo>OwnerAddress</Tipo>
						<Linea>1</Linea>
						<Texto>
							<Texto>CALLE 16 ESQ 19</Texto>
							<Atributos type="list">
							</Atributos>
						</Texto>
					</LineaUsuario>
					<LineaUsuario>
						<Orden>4</Orden>
						<Estacion>Ticket</Estacion>
						<Tipo>OwnerAddress</Tipo>
						<Linea>2</Linea>
						<Texto>
							<Texto>C.P.(3700)-PCIA. R. S. PEÑA-CHACO</Texto>
							<Atributos type="list">
							</Atributos>
						</Texto>
					</LineaUsuario>
					<LineaUsuario>
						<Orden>5</Orden>
						<Estacion>Ticket</Estacion>
						<Tipo>Fantasy</Tipo>
						<Linea>1</Linea>
						<Texto>
							<Texto>ÑANDEJARA CARNES</Texto>
							<Atributos type="list">
							</Atributos>
						</Texto>
					</LineaUsuario>
					<Apertura>
						<Orden>6</Orden>
						<TipoDocumento>DocumentoFiscal</TipoDocumento>
						<SubTipoDocumento>Factura</SubTipoDocumento>
						<CalificadorDocumento>B</CalificadorDocumento>
						<Estacion>Ticket</Estacion>
						<TipoAFIP>82</TipoAFIP>
						<POS>00011</POS>
						<Fecha>230130</Fecha>
						<Hora>183556</Hora>
						<NumeroDocumento>54750</NumeroDocumento>
						<NumeroCompleto>00011-00054750</NumeroCompleto>
						<IdentificadorCopia>Original</IdentificadorCopia>
					</Apertura>
					<Venta>
						<Orden>7</Orden>
						<Descripcion>COSTELETA DE TERNERA</Descripcion>
						<CodigoInterno>00224</CodigoInterno>
						<CodigoMatrix>00224</CodigoMatrix>
						<Cantidad>1.035</Cantidad>
						<UnidadesMatrix>0</UnidadesMatrix>
						<UnidadMedida>UM_KILO</UnidadMedida>
						<Precio>1495</Precio>
						<CondicionIVA>CondicionIVAGravado</CondicionIVA>
						<TasaIVA>10.5</TasaIVA>
						<ImpuestoComoCoeficiente>Sí</ImpuestoComoCoeficiente>
						<ImpInt>0</ImpInt>
						<ImpIntFijo>No</ImpIntFijo>
						<PorBaseImponible>No</PorBaseImponible>
						<Desglose>
							<Cantidad>1.035</Cantidad>
							<PrecioFinal>1495</PrecioFinal>
							<MontoFinal>1547.33</MontoFinal>
							<TasaIVA>10.5</TasaIVA>
							<PrecioBase>1352.9412</PrecioBase>
							<MontoTotalBase>1400.3</MontoTotalBase>
							<MontoTotalIVA>147.03</MontoTotalIVA>
							<MontoTotalII>0</MontoTotalII>
							<ImpIntFijo>No</ImpIntFijo>
							<ConceptosNoGravados>0</ConceptosNoGravados>
							<K>0</K>
						</Desglose>
					</Venta>
					<Venta>
						<Orden>8</Orden>
						<Descripcion>NALGA DE TERNERA</Descripcion>
						<CodigoInterno>00240</CodigoInterno>
						<CodigoMatrix>00240</CodigoMatrix>
						<Cantidad>2.98</Cantidad>
						<UnidadesMatrix>0</UnidadesMatrix>
						<UnidadMedida>UM_KILO</UnidadMedida>
						<Precio>1549</Precio>
						<CondicionIVA>CondicionIVAGravado</CondicionIVA>
						<TasaIVA>10.5</TasaIVA>
						<ImpuestoComoCoeficiente>Sí</ImpuestoComoCoeficiente>
						<ImpInt>0</ImpInt>
						<ImpIntFijo>No</ImpIntFijo>
						<PorBaseImponible>No</PorBaseImponible>
						<Desglose>
							<Cantidad>2.98</Cantidad>
							<PrecioFinal>1549</PrecioFinal>
							<MontoFinal>4616.02</MontoFinal>
							<TasaIVA>10.5</TasaIVA>
							<PrecioBase>1401.81</PrecioBase>
							<MontoTotalBase>4177.39</MontoTotalBase>
							<MontoTotalIVA>438.63</MontoTotalIVA>
							<MontoTotalII>0</MontoTotalII>
							<ImpIntFijo>No</ImpIntFijo>
							<ConceptosNoGravados>0</ConceptosNoGravados>
							<K>0</K>
						</Desglose>
					</Venta>
					<Venta>
						<Orden>9</Orden>
						<Descripcion>CARRE DE CERDO</Descripcion>
						<CodigoInterno>00019</CodigoInterno>
						<CodigoMatrix>00019</CodigoMatrix>
						<Cantidad>0.785</Cantidad>
						<UnidadesMatrix>0</UnidadesMatrix>
						<UnidadMedida>UM_KILO</UnidadMedida>
						<Precio>1154.505</Precio>
						<CondicionIVA>CondicionIVAGravado</CondicionIVA>
						<TasaIVA>10.5</TasaIVA>
						<ImpuestoComoCoeficiente>Sí</ImpuestoComoCoeficiente>
						<ImpInt>0</ImpInt>
						<ImpIntFijo>No</ImpIntFijo>
						<PorBaseImponible>No</PorBaseImponible>
						<Desglose>
							<Cantidad>0.785</Cantidad>
							<PrecioFinal>1154.505</PrecioFinal>
							<MontoFinal>906.29</MontoFinal>
							<TasaIVA>10.5</TasaIVA>
							<PrecioBase>1044.8009</PrecioBase>
							<MontoTotalBase>820.17</MontoTotalBase>
							<MontoTotalIVA>86.12</MontoTotalIVA>
							<MontoTotalII>0</MontoTotalII>
							<ImpIntFijo>No</ImpIntFijo>
							<ConceptosNoGravados>0</ConceptosNoGravados>
							<K>0</K>
						</Desglose>
					</Venta>
					<DiscriminacionIVA>
						<Orden>10</Orden>
						<CondicionIVA>CondicionIVAGravado</CondicionIVA>
						<TasaIVA>10.5</TasaIVA>
						<Base>6397.86</Base>
						<MontoIVA>671.78</MontoIVA>
					</DiscriminacionIVA>
					<Totales>
						<Orden>11</Orden>
						<Base>6397.86</Base>
						<MontoIVA>671.78</MontoIVA>
						<MontoII>0</MontoII>
						<MontoOtrosTributos>0</MontoOtrosTributos>
						<MontoNoGravado>0</MontoNoGravado>
						<MontoExento>0</MontoExento>
						<MontoGravado>6397.86</MontoGravado>
						<AjusteRedondeo>0</AjusteRedondeo>
						<Final>7069.64</Final>
						<ImpresionBase>6397.85</ImpresionBase>
						<ImpresionMontoIVA>671.78</ImpresionMontoIVA>
						<ImpresionMontoII>0</ImpresionMontoII>
						<ImpresionFinal>7069.64</ImpresionFinal>
						<TipoTotales>TotalesAlFinal</TipoTotales>
					</Totales>
					<Pago>
						<Orden>12</Orden>
						<EsCambio>No</EsCambio>
						<Monto>7069.64</Monto>
						<Descripcion>MAESTRO</Descripcion>
						<Tipo>PAGOS_TARJETA_DEBITO</Tipo>
						<Cuotas>0</Cuotas>
						<Desglose>
							<Monto>7069.64</Monto>
						</Desglose>
					</Pago>
					<Pago>
						<Orden>13</Orden>
						<EsCambio>Sí</EsCambio>
						<Monto>0</Monto>
						<Tipo>PAGOS_OTROS</Tipo>
						<Cuotas>0</Cuotas>
						<Desglose>
							<Monto>0</Monto>
						</Desglose>
					</Pago>
					<Cierre>
						<Orden>14</Orden>
						<TipoDocumento>DocumentoFiscal</TipoDocumento>
						<SubTipoDocumento>Factura</SubTipoDocumento>
						<CalificadorDocumento>B</CalificadorDocumento>
						<Estacion>Ticket</Estacion>
						<Registro>HSHSAB0000009658</Registro>
						<Version>01.00</Version>
						<NumeroDocumento>54750</NumeroDocumento>
						<NumeroCompleto>00011-00054750</NumeroCompleto>
						<Totales>
							<Total>7069.64</Total>
							<TotalBase>6397.86</TotalBase>
							<TotalNoGravado>0</TotalNoGravado>
							<TotalGravado>6397.86</TotalGravado>
							<TotalExento>0</TotalExento>
							<TotalIVA>671.78</TotalIVA>
							<TotalII>0</TotalII>
							<TotalOtrosTributos>0</TotalOtrosTributos>
							<TotalPagos>7069.64</TotalPagos>
							<OperacionesVenta>3</OperacionesVenta>
							<DiscriminacionIVA type="list">
								<IVA>
									<TasaIVA>10.5</TasaIVA>
									<ImpIntFijo>0</ImpIntFijo>
									<ImpIntVariable>0</ImpIntVariable>
									<NetoSinIVA>6397.86</NetoSinIVA>
									<MontoIVA>671.78</MontoIVA>
								</IVA>
							</DiscriminacionIVA>
							<DiscriminacionOtrosTributos type="list">
							</DiscriminacionOtrosTributos>
						</Totales>
					</Cierre>
				</Items>
			</Documento>
			<Documento>
				<Orden>6</Orden>
				<Items type="list">
					<Cliente>
						<Orden>0</Orden>
						<NroDocumento>1</NroDocumento>
						<NroSecuencia>1</NroSecuencia>
						<TipoDocumento>DNI</TipoDocumento>
						<TipoCliente>ClienteConsumidorFinal</TipoCliente>
						<Nombre>CONSUMIDOR FINAL</Nombre>
						<Direccion>.</Direccion>
					</Cliente>
					<AtributosImpresion>
						<Orden>1</Orden>
						<Personalidad>ImpresorFiscal</Personalidad>
						<Producto>SMH/PT-250F 6.02A</Producto>
						<Modelo>Hasar SMH/PT-250F 1.</Modelo>
						<ModeloImpresor>80250-64</ModeloImpresor>
						<Estacion>Ticket</Estacion>
						<AnchoPapel>64</AnchoPapel>
						<AltoPapel>0</AltoPapel>
						<TipoHojaAlto>AltoA4</TipoHojaAlto>
						<TipoHojaAncho>AnchoNormal</TipoHojaAncho>
						<ImprimeLeyendasOpcionales>Sí</ImprimeLeyendasOpcionales>
						<ImprimeCodigos>NoImprimeCodigos</ImprimeCodigos>
						<ImprimeUnidadesMedida>No</ImprimeUnidadesMedida>
						<ImprimeMarcos>No</ImprimeMarcos>
						<ModoEntrenamiento>No</ModoEntrenamiento>
						<SignoMonetario>$</SignoMonetario>
						<UsarColorAlternativo>No</UsarColorAlternativo>
						<ColorAlternativo>Negro</ColorAlternativo>
						<ImprimeQR>Sí</ImprimeQR>
						<TipoInterlineado>InterlineadoNormal</TipoInterlineado>
					</AtributosImpresion>
					<Emisor>
						<Orden>2</Orden>
						<CUIT>20347825604</CUIT>
						<RazonSocial>COLANERI SERGIO ALEJANDRO</RazonSocial>
						<NroRegistro>HSHSAB0000009658</NroRegistro>
						<FechaInicioActividades>20180901</FechaInicioActividades>
						<IngBrutos>20-34782560-4</IngBrutos>
						<TipoEmisor>EmisorInscripto</TipoEmisor>
						<TipoHabilitacion>ComprobantesA</TipoHabilitacion>
						<LimiteM>1000</LimiteM>
					</Emisor>
					<LineaUsuario>
						<Orden>3</Orden>
						<Estacion>Ticket</Estacion>
						<Tipo>OwnerAddress</Tipo>
						<Linea>1</Linea>
						<Texto>
							<Texto>CALLE 16 ESQ 19</Texto>
							<Atributos type="list">
							</Atributos>
						</Texto>
					</LineaUsuario>
					<LineaUsuario>
						<Orden>4</Orden>
						<Estacion>Ticket</Estacion>
						<Tipo>OwnerAddress</Tipo>
						<Linea>2</Linea>
						<Texto>
							<Texto>C.P.(3700)-PCIA. R. S. PEÑA-CHACO</Texto>
							<Atributos type="list">
							</Atributos>
						</Texto>
					</LineaUsuario>
					<LineaUsuario>
						<Orden>5</Orden>
						<Estacion>Ticket</Estacion>
						<Tipo>Fantasy</Tipo>
						<Linea>1</Linea>
						<Texto>
							<Texto>ÑANDEJARA CARNES</Texto>
							<Atributos type="list">
							</Atributos>
						</Texto>
					</LineaUsuario>
					<Apertura>
						<Orden>6</Orden>
						<TipoDocumento>DocumentoFiscal</TipoDocumento>
						<SubTipoDocumento>Factura</SubTipoDocumento>
						<CalificadorDocumento>B</CalificadorDocumento>
						<Estacion>Ticket</Estacion>
						<TipoAFIP>82</TipoAFIP>
						<POS>00011</POS>
						<Fecha>230130</Fecha>
						<Hora>185649</Hora>
						<NumeroDocumento>54751</NumeroDocumento>
						<NumeroCompleto>00011-00054751</NumeroCompleto>
						<IdentificadorCopia>Original</IdentificadorCopia>
					</Apertura>
					<Venta>
						<Orden>7</Orden>
						<Descripcion>MOLIDA ESPECIAL TERNERA</Descripcion>
						<CodigoInterno>00043</CodigoInterno>
						<CodigoMatrix>00043</CodigoMatrix>
						<Cantidad>0.6</Cantidad>
						<UnidadesMatrix>0</UnidadesMatrix>
						<UnidadMedida>UM_KILO</UnidadMedida>
						<Precio>1549</Precio>
						<CondicionIVA>CondicionIVAGravado</CondicionIVA>
						<TasaIVA>10.5</TasaIVA>
						<ImpuestoComoCoeficiente>Sí</ImpuestoComoCoeficiente>
						<ImpInt>0</ImpInt>
						<ImpIntFijo>No</ImpIntFijo>
						<PorBaseImponible>No</PorBaseImponible>
						<Desglose>
							<Cantidad>0.6</Cantidad>
							<PrecioFinal>1549</PrecioFinal>
							<MontoFinal>929.4</MontoFinal>
							<TasaIVA>10.5</TasaIVA>
							<PrecioBase>1401.81</PrecioBase>
							<MontoTotalBase>841.09</MontoTotalBase>
							<MontoTotalIVA>88.31</MontoTotalIVA>
							<MontoTotalII>0</MontoTotalII>
							<ImpIntFijo>No</ImpIntFijo>
							<ConceptosNoGravados>0</ConceptosNoGravados>
							<K>0</K>
						</Desglose>
					</Venta>
					<Venta>
						<Orden>8</Orden>
						<Descripcion>CARRE DE CERDO</Descripcion>
						<CodigoInterno>00019</CodigoInterno>
						<CodigoMatrix>00019</CodigoMatrix>
						<Cantidad>0.74</Cantidad>
						<UnidadesMatrix>0</UnidadesMatrix>
						<UnidadMedida>UM_KILO</UnidadMedida>
						<Precio>1154.505</Precio>
						<CondicionIVA>CondicionIVAGravado</CondicionIVA>
						<TasaIVA>10.5</TasaIVA>
						<ImpuestoComoCoeficiente>Sí</ImpuestoComoCoeficiente>
						<ImpInt>0</ImpInt>
						<ImpIntFijo>No</ImpIntFijo>
						<PorBaseImponible>No</PorBaseImponible>
						<Desglose>
							<Cantidad>0.74</Cantidad>
							<PrecioFinal>1154.505</PrecioFinal>
							<MontoFinal>854.33</MontoFinal>
							<TasaIVA>10.5</TasaIVA>
							<PrecioBase>1044.8009</PrecioBase>
							<MontoTotalBase>773.15</MontoTotalBase>
							<MontoTotalIVA>81.18</MontoTotalIVA>
							<MontoTotalII>0</MontoTotalII>
							<ImpIntFijo>No</ImpIntFijo>
							<ConceptosNoGravados>0</ConceptosNoGravados>
							<K>0</K>
						</Desglose>
					</Venta>
					<DiscriminacionIVA>
						<Orden>9</Orden>
						<CondicionIVA>CondicionIVAGravado</CondicionIVA>
						<TasaIVA>10.5</TasaIVA>
						<Base>1614.24</Base>
						<MontoIVA>169.49</MontoIVA>
					</DiscriminacionIVA>
					<Totales>
						<Orden>10</Orden>
						<Base>1614.24</Base>
						<MontoIVA>169.49</MontoIVA>
						<MontoII>0</MontoII>
						<MontoOtrosTributos>0</MontoOtrosTributos>
						<MontoNoGravado>0</MontoNoGravado>
						<MontoExento>0</MontoExento>
						<MontoGravado>1614.24</MontoGravado>
						<AjusteRedondeo>0</AjusteRedondeo>
						<Final>1783.73</Final>
						<ImpresionBase>1614.24</ImpresionBase>
						<ImpresionMontoIVA>169.49</ImpresionMontoIVA>
						<ImpresionMontoII>0</ImpresionMontoII>
						<ImpresionFinal>1783.73</ImpresionFinal>
						<TipoTotales>TotalesAlFinal</TipoTotales>
					</Totales>
					<Pago>
						<Orden>11</Orden>
						<EsCambio>No</EsCambio>
						<Monto>1783.73</Monto>
						<Descripcion>MAESTRO</Descripcion>
						<Tipo>PAGOS_TARJETA_DEBITO</Tipo>
						<Cuotas>0</Cuotas>
						<Desglose>
							<Monto>1783.73</Monto>
						</Desglose>
					</Pago>
					<Pago>
						<Orden>12</Orden>
						<EsCambio>Sí</EsCambio>
						<Monto>0</Monto>
						<Tipo>PAGOS_OTROS</Tipo>
						<Cuotas>0</Cuotas>
						<Desglose>
							<Monto>0</Monto>
						</Desglose>
					</Pago>
					<Cierre>
						<Orden>13</Orden>
						<TipoDocumento>DocumentoFiscal</TipoDocumento>
						<SubTipoDocumento>Factura</SubTipoDocumento>
						<CalificadorDocumento>B</CalificadorDocumento>
						<Estacion>Ticket</Estacion>
						<Registro>HSHSAB0000009658</Registro>
						<Version>01.00</Version>
						<NumeroDocumento>54751</NumeroDocumento>
						<NumeroCompleto>00011-00054751</NumeroCompleto>
						<Totales>
							<Total>1783.73</Total>
							<TotalBase>1614.24</TotalBase>
							<TotalNoGravado>0</TotalNoGravado>
							<TotalGravado>1614.24</TotalGravado>
							<TotalExento>0</TotalExento>
							<TotalIVA>169.49</TotalIVA>
							<TotalII>0</TotalII>
							<TotalOtrosTributos>0</TotalOtrosTributos>
							<TotalPagos>1783.73</TotalPagos>
							<OperacionesVenta>2</OperacionesVenta>
							<DiscriminacionIVA type="list">
								<IVA>
									<TasaIVA>10.5</TasaIVA>
									<ImpIntFijo>0</ImpIntFijo>
									<ImpIntVariable>0</ImpIntVariable>
									<NetoSinIVA>1614.24</NetoSinIVA>
									<MontoIVA>169.49</MontoIVA>
								</IVA>
							</DiscriminacionIVA>
							<DiscriminacionOtrosTributos type="list">
							</DiscriminacionOtrosTributos>
						</Totales>
					</Cierre>
				</Items>
			</Documento>
			<Documento>
				<Orden>7</Orden>
				<Items type="list">
					<Cliente>
						<Orden>0</Orden>
						<NroDocumento>1</NroDocumento>
						<NroSecuencia>1</NroSecuencia>
						<TipoDocumento>DNI</TipoDocumento>
						<TipoCliente>ClienteConsumidorFinal</TipoCliente>
						<Nombre>CONSUMIDOR FINAL</Nombre>
						<Direccion>.</Direccion>
					</Cliente>
					<AtributosImpresion>
						<Orden>1</Orden>
						<Personalidad>ImpresorFiscal</Personalidad>
						<Producto>SMH/PT-250F 6.02A</Producto>
						<Modelo>Hasar SMH/PT-250F 1.</Modelo>
						<ModeloImpresor>80250-64</ModeloImpresor>
						<Estacion>Ticket</Estacion>
						<AnchoPapel>64</AnchoPapel>
						<AltoPapel>0</AltoPapel>
						<TipoHojaAlto>AltoA4</TipoHojaAlto>
						<TipoHojaAncho>AnchoNormal</TipoHojaAncho>
						<ImprimeLeyendasOpcionales>Sí</ImprimeLeyendasOpcionales>
						<ImprimeCodigos>NoImprimeCodigos</ImprimeCodigos>
						<ImprimeUnidadesMedida>No</ImprimeUnidadesMedida>
						<ImprimeMarcos>No</ImprimeMarcos>
						<ModoEntrenamiento>No</ModoEntrenamiento>
						<SignoMonetario>$</SignoMonetario>
						<UsarColorAlternativo>No</UsarColorAlternativo>
						<ColorAlternativo>Negro</ColorAlternativo>
						<ImprimeQR>Sí</ImprimeQR>
						<TipoInterlineado>InterlineadoNormal</TipoInterlineado>
					</AtributosImpresion>
					<Emisor>
						<Orden>2</Orden>
						<CUIT>20347825604</CUIT>
						<RazonSocial>COLANERI SERGIO ALEJANDRO</RazonSocial>
						<NroRegistro>HSHSAB0000009658</NroRegistro>
						<FechaInicioActividades>20180901</FechaInicioActividades>
						<IngBrutos>20-34782560-4</IngBrutos>
						<TipoEmisor>EmisorInscripto</TipoEmisor>
						<TipoHabilitacion>ComprobantesA</TipoHabilitacion>
						<LimiteM>1000</LimiteM>
					</Emisor>
					<LineaUsuario>
						<Orden>3</Orden>
						<Estacion>Ticket</Estacion>
						<Tipo>OwnerAddress</Tipo>
						<Linea>1</Linea>
						<Texto>
							<Texto>CALLE 16 ESQ 19</Texto>
							<Atributos type="list">
							</Atributos>
						</Texto>
					</LineaUsuario>
					<LineaUsuario>
						<Orden>4</Orden>
						<Estacion>Ticket</Estacion>
						<Tipo>OwnerAddress</Tipo>
						<Linea>2</Linea>
						<Texto>
							<Texto>C.P.(3700)-PCIA. R. S. PEÑA-CHACO</Texto>
							<Atributos type="list">
							</Atributos>
						</Texto>
					</LineaUsuario>
					<LineaUsuario>
						<Orden>5</Orden>
						<Estacion>Ticket</Estacion>
						<Tipo>Fantasy</Tipo>
						<Linea>1</Linea>
						<Texto>
							<Texto>ÑANDEJARA CARNES</Texto>
							<Atributos type="list">
							</Atributos>
						</Texto>
					</LineaUsuario>
					<Apertura>
						<Orden>6</Orden>
						<TipoDocumento>DocumentoFiscal</TipoDocumento>
						<SubTipoDocumento>Factura</SubTipoDocumento>
						<CalificadorDocumento>B</CalificadorDocumento>
						<Estacion>Ticket</Estacion>
						<TipoAFIP>82</TipoAFIP>
						<POS>00011</POS>
						<Fecha>230130</Fecha>
						<Hora>192512</Hora>
						<NumeroDocumento>54752</NumeroDocumento>
						<NumeroCompleto>00011-00054752</NumeroCompleto>
						<IdentificadorCopia>Original</IdentificadorCopia>
					</Apertura>
					<Venta>
						<Orden>7</Orden>
						<Descripcion>AGUJA DE TERNERA</Descripcion>
						<CodigoInterno>00001</CodigoInterno>
						<CodigoMatrix>00001</CodigoMatrix>
						<Cantidad>2.43</Cantidad>
						<UnidadesMatrix>0</UnidadesMatrix>
						<UnidadMedida>UM_KILO</UnidadMedida>
						<Precio>1022.135</Precio>
						<CondicionIVA>CondicionIVAGravado</CondicionIVA>
						<TasaIVA>10.5</TasaIVA>
						<ImpuestoComoCoeficiente>Sí</ImpuestoComoCoeficiente>
						<ImpInt>0</ImpInt>
						<ImpIntFijo>No</ImpIntFijo>
						<PorBaseImponible>No</PorBaseImponible>
						<Desglose>
							<Cantidad>2.43</Cantidad>
							<PrecioFinal>1022.135</PrecioFinal>
							<MontoFinal>2483.79</MontoFinal>
							<TasaIVA>10.5</TasaIVA>
							<PrecioBase>925.009</PrecioBase>
							<MontoTotalBase>2247.77</MontoTotalBase>
							<MontoTotalIVA>236.02</MontoTotalIVA>
							<MontoTotalII>0</MontoTotalII>
							<ImpIntFijo>No</ImpIntFijo>
							<ConceptosNoGravados>0</ConceptosNoGravados>
							<K>0</K>
						</Desglose>
					</Venta>
					<DiscriminacionIVA>
						<Orden>8</Orden>
						<CondicionIVA>CondicionIVAGravado</CondicionIVA>
						<TasaIVA>10.5</TasaIVA>
						<Base>2247.77</Base>
						<MontoIVA>236.02</MontoIVA>
					</DiscriminacionIVA>
					<Totales>
						<Orden>9</Orden>
						<Base>2247.77</Base>
						<MontoIVA>236.02</MontoIVA>
						<MontoII>0</MontoII>
						<MontoOtrosTributos>0</MontoOtrosTributos>
						<MontoNoGravado>0</MontoNoGravado>
						<MontoExento>0</MontoExento>
						<MontoGravado>2247.77</MontoGravado>
						<AjusteRedondeo>0</AjusteRedondeo>
						<Final>2483.79</Final>
						<ImpresionBase>2247.77</ImpresionBase>
						<ImpresionMontoIVA>236.02</ImpresionMontoIVA>
						<ImpresionMontoII>0</ImpresionMontoII>
						<ImpresionFinal>2483.79</ImpresionFinal>
						<TipoTotales>TotalesAlFinal</TipoTotales>
					</Totales>
					<Pago>
						<Orden>10</Orden>
						<EsCambio>No</EsCambio>
						<Monto>2483.79</Monto>
						<Descripcion>EFECTIVO</Descripcion>
						<Tipo>PAGOS_EFECTIVO</Tipo>
						<Cuotas>0</Cuotas>
						<Desglose>
							<Monto>2483.79</Monto>
						</Desglose>
					</Pago>
					<Pago>
						<Orden>11</Orden>
						<EsCambio>Sí</EsCambio>
						<Monto>0</Monto>
						<Tipo>PAGOS_OTROS</Tipo>
						<Cuotas>0</Cuotas>
						<Desglose>
							<Monto>0</Monto>
						</Desglose>
					</Pago>
					<Cierre>
						<Orden>12</Orden>
						<TipoDocumento>DocumentoFiscal</TipoDocumento>
						<SubTipoDocumento>Factura</SubTipoDocumento>
						<CalificadorDocumento>B</CalificadorDocumento>
						<Estacion>Ticket</Estacion>
						<Registro>HSHSAB0000009658</Registro>
						<Version>01.00</Version>
						<NumeroDocumento>54752</NumeroDocumento>
						<NumeroCompleto>00011-00054752</NumeroCompleto>
						<Totales>
							<Total>2483.79</Total>
							<TotalBase>2247.77</TotalBase>
							<TotalNoGravado>0</TotalNoGravado>
							<TotalGravado>2247.77</TotalGravado>
							<TotalExento>0</TotalExento>
							<TotalIVA>236.02</TotalIVA>
							<TotalII>0</TotalII>
							<TotalOtrosTributos>0</TotalOtrosTributos>
							<TotalPagos>2483.79</TotalPagos>
							<OperacionesVenta>1</OperacionesVenta>
							<DiscriminacionIVA type="list">
								<IVA>
									<TasaIVA>10.5</TasaIVA>
									<ImpIntFijo>0</ImpIntFijo>
									<ImpIntVariable>0</ImpIntVariable>
									<NetoSinIVA>2247.77</NetoSinIVA>
									<MontoIVA>236.02</MontoIVA>
								</IVA>
							</DiscriminacionIVA>
							<DiscriminacionOtrosTributos type="list">
							</DiscriminacionOtrosTributos>
						</Totales>
					</Cierre>
				</Items>
			</Documento>
			<Documento>
				<Orden>8</Orden>
				<Items type="list">
					<Cliente>
						<Orden>0</Orden>
						<NroDocumento>1</NroDocumento>
						<NroSecuencia>1</NroSecuencia>
						<TipoDocumento>DNI</TipoDocumento>
						<TipoCliente>ClienteConsumidorFinal</TipoCliente>
						<Nombre>CONSUMIDOR FINAL</Nombre>
						<Direccion>.</Direccion>
					</Cliente>
					<AtributosImpresion>
						<Orden>1</Orden>
						<Personalidad>ImpresorFiscal</Personalidad>
						<Producto>SMH/PT-250F 6.02A</Producto>
						<Modelo>Hasar SMH/PT-250F 1.</Modelo>
						<ModeloImpresor>80250-64</ModeloImpresor>
						<Estacion>Ticket</Estacion>
						<AnchoPapel>64</AnchoPapel>
						<AltoPapel>0</AltoPapel>
						<TipoHojaAlto>AltoA4</TipoHojaAlto>
						<TipoHojaAncho>AnchoNormal</TipoHojaAncho>
						<ImprimeLeyendasOpcionales>Sí</ImprimeLeyendasOpcionales>
						<ImprimeCodigos>NoImprimeCodigos</ImprimeCodigos>
						<ImprimeUnidadesMedida>No</ImprimeUnidadesMedida>
						<ImprimeMarcos>No</ImprimeMarcos>
						<ModoEntrenamiento>No</ModoEntrenamiento>
						<SignoMonetario>$</SignoMonetario>
						<UsarColorAlternativo>No</UsarColorAlternativo>
						<ColorAlternativo>Negro</ColorAlternativo>
						<ImprimeQR>Sí</ImprimeQR>
						<TipoInterlineado>InterlineadoNormal</TipoInterlineado>
					</AtributosImpresion>
					<Emisor>
						<Orden>2</Orden>
						<CUIT>20347825604</CUIT>
						<RazonSocial>COLANERI SERGIO ALEJANDRO</RazonSocial>
						<NroRegistro>HSHSAB0000009658</NroRegistro>
						<FechaInicioActividades>20180901</FechaInicioActividades>
						<IngBrutos>20-34782560-4</IngBrutos>
						<TipoEmisor>EmisorInscripto</TipoEmisor>
						<TipoHabilitacion>ComprobantesA</TipoHabilitacion>
						<LimiteM>1000</LimiteM>
					</Emisor>
					<LineaUsuario>
						<Orden>3</Orden>
						<Estacion>Ticket</Estacion>
						<Tipo>OwnerAddress</Tipo>
						<Linea>1</Linea>
						<Texto>
							<Texto>CALLE 16 ESQ 19</Texto>
							<Atributos type="list">
							</Atributos>
						</Texto>
					</LineaUsuario>
					<LineaUsuario>
						<Orden>4</Orden>
						<Estacion>Ticket</Estacion>
						<Tipo>OwnerAddress</Tipo>
						<Linea>2</Linea>
						<Texto>
							<Texto>C.P.(3700)-PCIA. R. S. PEÑA-CHACO</Texto>
							<Atributos type="list">
							</Atributos>
						</Texto>
					</LineaUsuario>
					<LineaUsuario>
						<Orden>5</Orden>
						<Estacion>Ticket</Estacion>
						<Tipo>Fantasy</Tipo>
						<Linea>1</Linea>
						<Texto>
							<Texto>ÑANDEJARA CARNES</Texto>
							<Atributos type="list">
							</Atributos>
						</Texto>
					</LineaUsuario>
					<Apertura>
						<Orden>6</Orden>
						<TipoDocumento>DocumentoFiscal</TipoDocumento>
						<SubTipoDocumento>Factura</SubTipoDocumento>
						<CalificadorDocumento>B</CalificadorDocumento>
						<Estacion>Ticket</Estacion>
						<TipoAFIP>82</TipoAFIP>
						<POS>00011</POS>
						<Fecha>230130</Fecha>
						<Hora>193452</Hora>
						<NumeroDocumento>54753</NumeroDocumento>
						<NumeroCompleto>00011-00054753</NumeroCompleto>
						<IdentificadorCopia>Original</IdentificadorCopia>
					</Apertura>
					<Venta>
						<Orden>7</Orden>
						<Descripcion>MILA DE TERNERA</Descripcion>
						<CodigoInterno>00101</CodigoInterno>
						<CodigoMatrix>00101</CodigoMatrix>
						<Cantidad>0.415</Cantidad>
						<UnidadesMatrix>0</UnidadesMatrix>
						<UnidadMedida>UM_KILO</UnidadMedida>
						<Precio>1495</Precio>
						<CondicionIVA>CondicionIVAGravado</CondicionIVA>
						<TasaIVA>10.5</TasaIVA>
						<ImpuestoComoCoeficiente>Sí</ImpuestoComoCoeficiente>
						<ImpInt>0</ImpInt>
						<ImpIntFijo>No</ImpIntFijo>
						<PorBaseImponible>No</PorBaseImponible>
						<Desglose>
							<Cantidad>0.415</Cantidad>
							<PrecioFinal>1495</PrecioFinal>
							<MontoFinal>620.43</MontoFinal>
							<TasaIVA>10.5</TasaIVA>
							<PrecioBase>1352.9412</PrecioBase>
							<MontoTotalBase>561.48</MontoTotalBase>
							<MontoTotalIVA>58.95</MontoTotalIVA>
							<MontoTotalII>0</MontoTotalII>
							<ImpIntFijo>No</ImpIntFijo>
							<ConceptosNoGravados>0</ConceptosNoGravados>
							<K>0</K>
						</Desglose>
					</Venta>
					<Venta>
						<Orden>8</Orden>
						<Descripcion>COSTELETA DE TERNERA</Descripcion>
						<CodigoInterno>00224</CodigoInterno>
						<CodigoMatrix>00224</CodigoMatrix>
						<Cantidad>0.715</Cantidad>
						<UnidadesMatrix>0</UnidadesMatrix>
						<UnidadMedida>UM_KILO</UnidadMedida>
						<Precio>1495</Precio>
						<CondicionIVA>CondicionIVAGravado</CondicionIVA>
						<TasaIVA>10.5</TasaIVA>
						<ImpuestoComoCoeficiente>Sí</ImpuestoComoCoeficiente>
						<ImpInt>0</ImpInt>
						<ImpIntFijo>No</ImpIntFijo>
						<PorBaseImponible>No</PorBaseImponible>
						<Desglose>
							<Cantidad>0.715</Cantidad>
							<PrecioFinal>1495</PrecioFinal>
							<MontoFinal>1068.93</MontoFinal>
							<TasaIVA>10.5</TasaIVA>
							<PrecioBase>1352.9412</PrecioBase>
							<MontoTotalBase>967.36</MontoTotalBase>
							<MontoTotalIVA>101.57</MontoTotalIVA>
							<MontoTotalII>0</MontoTotalII>
							<ImpIntFijo>No</ImpIntFijo>
							<ConceptosNoGravados>0</ConceptosNoGravados>
							<K>0</K>
						</Desglose>
					</Venta>
					<DiscriminacionIVA>
						<Orden>9</Orden>
						<CondicionIVA>CondicionIVAGravado</CondicionIVA>
						<TasaIVA>10.5</TasaIVA>
						<Base>1528.84</Base>
						<MontoIVA>160.52</MontoIVA>
					</DiscriminacionIVA>
					<Totales>
						<Orden>10</Orden>
						<Base>1528.84</Base>
						<MontoIVA>160.52</MontoIVA>
						<MontoII>0</MontoII>
						<MontoOtrosTributos>0</MontoOtrosTributos>
						<MontoNoGravado>0</MontoNoGravado>
						<MontoExento>0</MontoExento>
						<MontoGravado>1528.84</MontoGravado>
						<AjusteRedondeo>0</AjusteRedondeo>
						<Final>1689.36</Final>
						<ImpresionBase>1528.82</ImpresionBase>
						<ImpresionMontoIVA>160.52</ImpresionMontoIVA>
						<ImpresionMontoII>0</ImpresionMontoII>
						<ImpresionFinal>1689.36</ImpresionFinal>
						<TipoTotales>TotalesAlFinal</TipoTotales>
					</Totales>
					<Pago>
						<Orden>11</Orden>
						<EsCambio>No</EsCambio>
						<Monto>1689.36</Monto>
						<Descripcion>MAESTRO</Descripcion>
						<Tipo>PAGOS_TARJETA_DEBITO</Tipo>
						<Cuotas>0</Cuotas>
						<Desglose>
							<Monto>1689.36</Monto>
						</Desglose>
					</Pago>
					<Pago>
						<Orden>12</Orden>
						<EsCambio>Sí</EsCambio>
						<Monto>0</Monto>
						<Tipo>PAGOS_OTROS</Tipo>
						<Cuotas>0</Cuotas>
						<Desglose>
							<Monto>0</Monto>
						</Desglose>
					</Pago>
					<Cierre>
						<Orden>13</Orden>
						<TipoDocumento>DocumentoFiscal</TipoDocumento>
						<SubTipoDocumento>Factura</SubTipoDocumento>
						<CalificadorDocumento>B</CalificadorDocumento>
						<Estacion>Ticket</Estacion>
						<Registro>HSHSAB0000009658</Registro>
						<Version>01.00</Version>
						<NumeroDocumento>54753</NumeroDocumento>
						<NumeroCompleto>00011-00054753</NumeroCompleto>
						<Totales>
							<Total>1689.36</Total>
							<TotalBase>1528.84</TotalBase>
							<TotalNoGravado>0</TotalNoGravado>
							<TotalGravado>1528.84</TotalGravado>
							<TotalExento>0</TotalExento>
							<TotalIVA>160.52</TotalIVA>
							<TotalII>0</TotalII>
							<TotalOtrosTributos>0</TotalOtrosTributos>
							<TotalPagos>1689.36</TotalPagos>
							<OperacionesVenta>2</OperacionesVenta>
							<DiscriminacionIVA type="list">
								<IVA>
									<TasaIVA>10.5</TasaIVA>
									<ImpIntFijo>0</ImpIntFijo>
									<ImpIntVariable>0</ImpIntVariable>
									<NetoSinIVA>1528.84</NetoSinIVA>
									<MontoIVA>160.52</MontoIVA>
								</IVA>
							</DiscriminacionIVA>
							<DiscriminacionOtrosTributos type="list">
							</DiscriminacionOtrosTributos>
						</Totales>
					</Cierre>
				</Items>
			</Documento>
			<Documento>
				<Orden>9</Orden>
				<Items type="list">
					<Cliente>
						<Orden>0</Orden>
						<NroDocumento>1</NroDocumento>
						<NroSecuencia>1</NroSecuencia>
						<TipoDocumento>DNI</TipoDocumento>
						<TipoCliente>ClienteConsumidorFinal</TipoCliente>
						<Nombre>CONSUMIDOR FINAL</Nombre>
						<Direccion>.</Direccion>
					</Cliente>
					<AtributosImpresion>
						<Orden>1</Orden>
						<Personalidad>ImpresorFiscal</Personalidad>
						<Producto>SMH/PT-250F 6.02A</Producto>
						<Modelo>Hasar SMH/PT-250F 1.</Modelo>
						<ModeloImpresor>80250-64</ModeloImpresor>
						<Estacion>Ticket</Estacion>
						<AnchoPapel>64</AnchoPapel>
						<AltoPapel>0</AltoPapel>
						<TipoHojaAlto>AltoA4</TipoHojaAlto>
						<TipoHojaAncho>AnchoNormal</TipoHojaAncho>
						<ImprimeLeyendasOpcionales>Sí</ImprimeLeyendasOpcionales>
						<ImprimeCodigos>NoImprimeCodigos</ImprimeCodigos>
						<ImprimeUnidadesMedida>No</ImprimeUnidadesMedida>
						<ImprimeMarcos>No</ImprimeMarcos>
						<ModoEntrenamiento>No</ModoEntrenamiento>
						<SignoMonetario>$</SignoMonetario>
						<UsarColorAlternativo>No</UsarColorAlternativo>
						<ColorAlternativo>Negro</ColorAlternativo>
						<ImprimeQR>Sí</ImprimeQR>
						<TipoInterlineado>InterlineadoNormal</TipoInterlineado>
					</AtributosImpresion>
					<Emisor>
						<Orden>2</Orden>
						<CUIT>20347825604</CUIT>
						<RazonSocial>COLANERI SERGIO ALEJANDRO</RazonSocial>
						<NroRegistro>HSHSAB0000009658</NroRegistro>
						<FechaInicioActividades>20180901</FechaInicioActividades>
						<IngBrutos>20-34782560-4</IngBrutos>
						<TipoEmisor>EmisorInscripto</TipoEmisor>
						<TipoHabilitacion>ComprobantesA</TipoHabilitacion>
						<LimiteM>1000</LimiteM>
					</Emisor>
					<LineaUsuario>
						<Orden>3</Orden>
						<Estacion>Ticket</Estacion>
						<Tipo>OwnerAddress</Tipo>
						<Linea>1</Linea>
						<Texto>
							<Texto>CALLE 16 ESQ 19</Texto>
							<Atributos type="list">
							</Atributos>
						</Texto>
					</LineaUsuario>
					<LineaUsuario>
						<Orden>4</Orden>
						<Estacion>Ticket</Estacion>
						<Tipo>OwnerAddress</Tipo>
						<Linea>2</Linea>
						<Texto>
							<Texto>C.P.(3700)-PCIA. R. S. PEÑA-CHACO</Texto>
							<Atributos type="list">
							</Atributos>
						</Texto>
					</LineaUsuario>
					<LineaUsuario>
						<Orden>5</Orden>
						<Estacion>Ticket</Estacion>
						<Tipo>Fantasy</Tipo>
						<Linea>1</Linea>
						<Texto>
							<Texto>ÑANDEJARA CARNES</Texto>
							<Atributos type="list">
							</Atributos>
						</Texto>
					</LineaUsuario>
					<Apertura>
						<Orden>6</Orden>
						<TipoDocumento>DocumentoFiscal</TipoDocumento>
						<SubTipoDocumento>Factura</SubTipoDocumento>
						<CalificadorDocumento>B</CalificadorDocumento>
						<Estacion>Ticket</Estacion>
						<TipoAFIP>82</TipoAFIP>
						<POS>00011</POS>
						<Fecha>230130</Fecha>
						<Hora>194134</Hora>
						<NumeroDocumento>54754</NumeroDocumento>
						<NumeroCompleto>00011-00054754</NumeroCompleto>
						<IdentificadorCopia>Original</IdentificadorCopia>
					</Apertura>
					<Venta>
						<Orden>7</Orden>
						<Descripcion>CUADRADA DE TERNERA</Descripcion>
						<CodigoInterno>00223</CodigoInterno>
						<CodigoMatrix>00223</CodigoMatrix>
						<Cantidad>0.68</Cantidad>
						<UnidadesMatrix>0</UnidadesMatrix>
						<UnidadMedida>UM_KILO</UnidadMedida>
						<Precio>1549</Precio>
						<CondicionIVA>CondicionIVAGravado</CondicionIVA>
						<TasaIVA>10.5</TasaIVA>
						<ImpuestoComoCoeficiente>Sí</ImpuestoComoCoeficiente>
						<ImpInt>0</ImpInt>
						<ImpIntFijo>No</ImpIntFijo>
						<PorBaseImponible>No</PorBaseImponible>
						<Desglose>
							<Cantidad>0.68</Cantidad>
							<PrecioFinal>1549</PrecioFinal>
							<MontoFinal>1053.32</MontoFinal>
							<TasaIVA>10.5</TasaIVA>
							<PrecioBase>1401.81</PrecioBase>
							<MontoTotalBase>953.23</MontoTotalBase>
							<MontoTotalIVA>100.09</MontoTotalIVA>
							<MontoTotalII>0</MontoTotalII>
							<ImpIntFijo>No</ImpIntFijo>
							<ConceptosNoGravados>0</ConceptosNoGravados>
							<K>0</K>
						</Desglose>
					</Venta>
					<DiscriminacionIVA>
						<Orden>8</Orden>
						<CondicionIVA>CondicionIVAGravado</CondicionIVA>
						<TasaIVA>10.5</TasaIVA>
						<Base>953.23</Base>
						<MontoIVA>100.09</MontoIVA>
					</DiscriminacionIVA>
					<Totales>
						<Orden>9</Orden>
						<Base>953.23</Base>
						<MontoIVA>100.09</MontoIVA>
						<MontoII>0</MontoII>
						<MontoOtrosTributos>0</MontoOtrosTributos>
						<MontoNoGravado>0</MontoNoGravado>
						<MontoExento>0</MontoExento>
						<MontoGravado>953.23</MontoGravado>
						<AjusteRedondeo>0</AjusteRedondeo>
						<Final>1053.32</Final>
						<ImpresionBase>953.23</ImpresionBase>
						<ImpresionMontoIVA>100.09</ImpresionMontoIVA>
						<ImpresionMontoII>0</ImpresionMontoII>
						<ImpresionFinal>1053.32</ImpresionFinal>
						<TipoTotales>TotalesAlFinal</TipoTotales>
					</Totales>
					<Pago>
						<Orden>10</Orden>
						<EsCambio>No</EsCambio>
						<Monto>1053.32</Monto>
						<Descripcion>EFECTIVO</Descripcion>
						<Tipo>PAGOS_EFECTIVO</Tipo>
						<Cuotas>0</Cuotas>
						<Desglose>
							<Monto>1053.32</Monto>
						</Desglose>
					</Pago>
					<Pago>
						<Orden>11</Orden>
						<EsCambio>Sí</EsCambio>
						<Monto>0</Monto>
						<Tipo>PAGOS_OTROS</Tipo>
						<Cuotas>0</Cuotas>
						<Desglose>
							<Monto>0</Monto>
						</Desglose>
					</Pago>
					<Cierre>
						<Orden>12</Orden>
						<TipoDocumento>DocumentoFiscal</TipoDocumento>
						<SubTipoDocumento>Factura</SubTipoDocumento>
						<CalificadorDocumento>B</CalificadorDocumento>
						<Estacion>Ticket</Estacion>
						<Registro>HSHSAB0000009658</Registro>
						<Version>01.00</Version>
						<NumeroDocumento>54754</NumeroDocumento>
						<NumeroCompleto>00011-00054754</NumeroCompleto>
						<Totales>
							<Total>1053.32</Total>
							<TotalBase>953.23</TotalBase>
							<TotalNoGravado>0</TotalNoGravado>
							<TotalGravado>953.23</TotalGravado>
							<TotalExento>0</TotalExento>
							<TotalIVA>100.09</TotalIVA>
							<TotalII>0</TotalII>
							<TotalOtrosTributos>0</TotalOtrosTributos>
							<TotalPagos>1053.32</TotalPagos>
							<OperacionesVenta>1</OperacionesVenta>
							<DiscriminacionIVA type="list">
								<IVA>
									<TasaIVA>10.5</TasaIVA>
									<ImpIntFijo>0</ImpIntFijo>
									<ImpIntVariable>0</ImpIntVariable>
									<NetoSinIVA>953.23</NetoSinIVA>
									<MontoIVA>100.09</MontoIVA>
								</IVA>
							</DiscriminacionIVA>
							<DiscriminacionOtrosTributos type="list">
							</DiscriminacionOtrosTributos>
						</Totales>
					</Cierre>
				</Items>
			</Documento>
			<Documento>
				<Orden>10</Orden>
				<Items type="list">
					<Cliente>
						<Orden>0</Orden>
						<NroDocumento>1</NroDocumento>
						<NroSecuencia>1</NroSecuencia>
						<TipoDocumento>DNI</TipoDocumento>
						<TipoCliente>ClienteConsumidorFinal</TipoCliente>
						<Nombre>CONSUMIDOR FINAL</Nombre>
						<Direccion>.</Direccion>
					</Cliente>
					<AtributosImpresion>
						<Orden>1</Orden>
						<Personalidad>ImpresorFiscal</Personalidad>
						<Producto>SMH/PT-250F 6.02A</Producto>
						<Modelo>Hasar SMH/PT-250F 1.</Modelo>
						<ModeloImpresor>80250-64</ModeloImpresor>
						<Estacion>Ticket</Estacion>
						<AnchoPapel>64</AnchoPapel>
						<AltoPapel>0</AltoPapel>
						<TipoHojaAlto>AltoA4</TipoHojaAlto>
						<TipoHojaAncho>AnchoNormal</TipoHojaAncho>
						<ImprimeLeyendasOpcionales>Sí</ImprimeLeyendasOpcionales>
						<ImprimeCodigos>NoImprimeCodigos</ImprimeCodigos>
						<ImprimeUnidadesMedida>No</ImprimeUnidadesMedida>
						<ImprimeMarcos>No</ImprimeMarcos>
						<ModoEntrenamiento>No</ModoEntrenamiento>
						<SignoMonetario>$</SignoMonetario>
						<UsarColorAlternativo>No</UsarColorAlternativo>
						<ColorAlternativo>Negro</ColorAlternativo>
						<ImprimeQR>Sí</ImprimeQR>
						<TipoInterlineado>InterlineadoNormal</TipoInterlineado>
					</AtributosImpresion>
					<Emisor>
						<Orden>2</Orden>
						<CUIT>20347825604</CUIT>
						<RazonSocial>COLANERI SERGIO ALEJANDRO</RazonSocial>
						<NroRegistro>HSHSAB0000009658</NroRegistro>
						<FechaInicioActividades>20180901</FechaInicioActividades>
						<IngBrutos>20-34782560-4</IngBrutos>
						<TipoEmisor>EmisorInscripto</TipoEmisor>
						<TipoHabilitacion>ComprobantesA</TipoHabilitacion>
						<LimiteM>1000</LimiteM>
					</Emisor>
					<LineaUsuario>
						<Orden>3</Orden>
						<Estacion>Ticket</Estacion>
						<Tipo>OwnerAddress</Tipo>
						<Linea>1</Linea>
						<Texto>
							<Texto>CALLE 16 ESQ 19</Texto>
							<Atributos type="list">
							</Atributos>
						</Texto>
					</LineaUsuario>
					<LineaUsuario>
						<Orden>4</Orden>
						<Estacion>Ticket</Estacion>
						<Tipo>OwnerAddress</Tipo>
						<Linea>2</Linea>
						<Texto>
							<Texto>C.P.(3700)-PCIA. R. S. PEÑA-CHACO</Texto>
							<Atributos type="list">
							</Atributos>
						</Texto>
					</LineaUsuario>
					<LineaUsuario>
						<Orden>5</Orden>
						<Estacion>Ticket</Estacion>
						<Tipo>Fantasy</Tipo>
						<Linea>1</Linea>
						<Texto>
							<Texto>ÑANDEJARA CARNES</Texto>
							<Atributos type="list">
							</Atributos>
						</Texto>
					</LineaUsuario>
					<Apertura>
						<Orden>6</Orden>
						<TipoDocumento>DocumentoFiscal</TipoDocumento>
						<SubTipoDocumento>Factura</SubTipoDocumento>
						<CalificadorDocumento>B</CalificadorDocumento>
						<Estacion>Ticket</Estacion>
						<TipoAFIP>82</TipoAFIP>
						<POS>00011</POS>
						<Fecha>230130</Fecha>
						<Hora>200402</Hora>
						<NumeroDocumento>54755</NumeroDocumento>
						<NumeroCompleto>00011-00054755</NumeroCompleto>
						<IdentificadorCopia>Original</IdentificadorCopia>
					</Apertura>
					<Venta>
						<Orden>7</Orden>
						<Descripcion>COSTELETA DE TERNERA</Descripcion>
						<CodigoInterno>00224</CodigoInterno>
						<CodigoMatrix>00224</CodigoMatrix>
						<Cantidad>1.01</Cantidad>
						<UnidadesMatrix>0</UnidadesMatrix>
						<UnidadMedida>UM_KILO</UnidadMedida>
						<Precio>1495</Precio>
						<CondicionIVA>CondicionIVAGravado</CondicionIVA>
						<TasaIVA>10.5</TasaIVA>
						<ImpuestoComoCoeficiente>Sí</ImpuestoComoCoeficiente>
						<ImpInt>0</ImpInt>
						<ImpIntFijo>No</ImpIntFijo>
						<PorBaseImponible>No</PorBaseImponible>
						<Desglose>
							<Cantidad>1.01</Cantidad>
							<PrecioFinal>1495</PrecioFinal>
							<MontoFinal>1509.95</MontoFinal>
							<TasaIVA>10.5</TasaIVA>
							<PrecioBase>1352.9412</PrecioBase>
							<MontoTotalBase>1366.47</MontoTotalBase>
							<MontoTotalIVA>143.48</MontoTotalIVA>
							<MontoTotalII>0</MontoTotalII>
							<ImpIntFijo>No</ImpIntFijo>
							<ConceptosNoGravados>0</ConceptosNoGravados>
							<K>0</K>
						</Desglose>
					</Venta>
					<Venta>
						<Orden>8</Orden>
						<Descripcion>COLITA DE CUADRIL-TERNERA</Descripcion>
						<CodigoInterno>00225</CodigoInterno>
						<CodigoMatrix>00225</CodigoMatrix>
						<Cantidad>0.655</Cantidad>
						<UnidadesMatrix>0</UnidadesMatrix>
						<UnidadMedida>UM_KILO</UnidadMedida>
						<Precio>1549</Precio>
						<CondicionIVA>CondicionIVAGravado</CondicionIVA>
						<TasaIVA>10.5</TasaIVA>
						<ImpuestoComoCoeficiente>Sí</ImpuestoComoCoeficiente>
						<ImpInt>0</ImpInt>
						<ImpIntFijo>No</ImpIntFijo>
						<PorBaseImponible>No</PorBaseImponible>
						<Desglose>
							<Cantidad>0.655</Cantidad>
							<PrecioFinal>1549</PrecioFinal>
							<MontoFinal>1014.6</MontoFinal>
							<TasaIVA>10.5</TasaIVA>
							<PrecioBase>1401.81</PrecioBase>
							<MontoTotalBase>918.19</MontoTotalBase>
							<MontoTotalIVA>96.41</MontoTotalIVA>
							<MontoTotalII>0</MontoTotalII>
							<ImpIntFijo>No</ImpIntFijo>
							<ConceptosNoGravados>0</ConceptosNoGravados>
							<K>0</K>
						</Desglose>
					</Venta>
					<DiscriminacionIVA>
						<Orden>9</Orden>
						<CondicionIVA>CondicionIVAGravado</CondicionIVA>
						<TasaIVA>10.5</TasaIVA>
						<Base>2284.66</Base>
						<MontoIVA>239.89</MontoIVA>
					</DiscriminacionIVA>
					<Totales>
						<Orden>10</Orden>
						<Base>2284.66</Base>
						<MontoIVA>239.89</MontoIVA>
						<MontoII>0</MontoII>
						<MontoOtrosTributos>0</MontoOtrosTributos>
						<MontoNoGravado>0</MontoNoGravado>
						<MontoExento>0</MontoExento>
						<MontoGravado>2284.66</MontoGravado>
						<AjusteRedondeo>0</AjusteRedondeo>
						<Final>2524.55</Final>
						<ImpresionBase>2284.66</ImpresionBase>
						<ImpresionMontoIVA>239.89</ImpresionMontoIVA>
						<ImpresionMontoII>0</ImpresionMontoII>
						<ImpresionFinal>2524.55</ImpresionFinal>
						<TipoTotales>TotalesAlFinal</TipoTotales>
					</Totales>
					<Pago>
						<Orden>11</Orden>
						<EsCambio>No</EsCambio>
						<Monto>2524.54</Monto>
						<Descripcion>EFECTIVO</Descripcion>
						<Tipo>PAGOS_EFECTIVO</Tipo>
						<Cuotas>0</Cuotas>
						<Desglose>
							<Monto>2524.54</Monto>
						</Desglose>
					</Pago>
					<Pago>
						<Orden>12</Orden>
						<EsCambio>No</EsCambio>
						<Monto>0.01</Monto>
						<Descripcion>Saldo</Descripcion>
						<Tipo>PAGOS_SALDO</Tipo>
						<Cuotas>0</Cuotas>
						<Desglose>
							<Monto>0.01</Monto>
						</Desglose>
					</Pago>
					<Cierre>
						<Orden>13</Orden>
						<TipoDocumento>DocumentoFiscal</TipoDocumento>
						<SubTipoDocumento>Factura</SubTipoDocumento>
						<CalificadorDocumento>B</CalificadorDocumento>
						<Estacion>Ticket</Estacion>
						<Registro>HSHSAB0000009658</Registro>
						<Version>01.00</Version>
						<NumeroDocumento>54755</NumeroDocumento>
						<NumeroCompleto>00011-00054755</NumeroCompleto>
						<Totales>
							<Total>2524.55</Total>
							<TotalBase>2284.66</TotalBase>
							<TotalNoGravado>0</TotalNoGravado>
							<TotalGravado>2284.66</TotalGravado>
							<TotalExento>0</TotalExento>
							<TotalIVA>239.89</TotalIVA>
							<TotalII>0</TotalII>
							<TotalOtrosTributos>0</TotalOtrosTributos>
							<TotalPagos>2524.55</TotalPagos>
							<OperacionesVenta>2</OperacionesVenta>
							<DiscriminacionIVA type="list">
								<IVA>
									<TasaIVA>10.5</TasaIVA>
									<ImpIntFijo>0</ImpIntFijo>
									<ImpIntVariable>0</ImpIntVariable>
									<NetoSinIVA>2284.66</NetoSinIVA>
									<MontoIVA>239.89</MontoIVA>
								</IVA>
							</DiscriminacionIVA>
							<DiscriminacionOtrosTributos type="list">
							</DiscriminacionOtrosTributos>
						</Totales>
					</Cierre>
				</Items>
			</Documento>
			<Documento>
				<Orden>11</Orden>
				<Items type="list">
					<AtributosImpresion>
						<Orden>0</Orden>
						<Personalidad>ImpresorFiscal</Personalidad>
						<Producto>SMH/PT-250F 6.02A</Producto>
						<Modelo>Hasar SMH/PT-250F 1.</Modelo>
						<ModeloImpresor>80250-64</ModeloImpresor>
						<Estacion>Ticket</Estacion>
						<AnchoPapel>64</AnchoPapel>
						<AltoPapel>0</AltoPapel>
						<TipoHojaAlto>AltoA4</TipoHojaAlto>
						<TipoHojaAncho>AnchoNormal</TipoHojaAncho>
						<ImprimeLeyendasOpcionales>Sí</ImprimeLeyendasOpcionales>
						<ImprimeCodigos>NoImprimeCodigos</ImprimeCodigos>
						<ImprimeUnidadesMedida>No</ImprimeUnidadesMedida>
						<ImprimeMarcos>No</ImprimeMarcos>
						<ModoEntrenamiento>No</ModoEntrenamiento>
						<SignoMonetario>$</SignoMonetario>
						<UsarColorAlternativo>No</UsarColorAlternativo>
						<ColorAlternativo>Negro</ColorAlternativo>
						<ImprimeQR>Sí</ImprimeQR>
						<TipoInterlineado>InterlineadoNormal</TipoInterlineado>
					</AtributosImpresion>
					<Emisor>
						<Orden>1</Orden>
						<CUIT>20347825604</CUIT>
						<RazonSocial>COLANERI SERGIO ALEJANDRO</RazonSocial>
						<NroRegistro>HSHSAB0000009658</NroRegistro>
						<FechaInicioActividades>20180901</FechaInicioActividades>
						<IngBrutos>20-34782560-4</IngBrutos>
						<TipoEmisor>EmisorInscripto</TipoEmisor>
						<TipoHabilitacion>ComprobantesA</TipoHabilitacion>
						<LimiteM>1000</LimiteM>
					</Emisor>
					<LineaUsuario>
						<Orden>2</Orden>
						<Estacion>Ticket</Estacion>
						<Tipo>OwnerAddress</Tipo>
						<Linea>1</Linea>
						<Texto>
							<Texto>CALLE 16 ESQ 19</Texto>
							<Atributos type="list">
							</Atributos>
						</Texto>
					</LineaUsuario>
					<LineaUsuario>
						<Orden>3</Orden>
						<Estacion>Ticket</Estacion>
						<Tipo>OwnerAddress</Tipo>
						<Linea>2</Linea>
						<Texto>
							<Texto>C.P.(3700)-PCIA. R. S. PEÑA-CHACO</Texto>
							<Atributos type="list">
							</Atributos>
						</Texto>
					</LineaUsuario>
					<LineaUsuario>
						<Orden>4</Orden>
						<Estacion>Ticket</Estacion>
						<Tipo>Fantasy</Tipo>
						<Linea>1</Linea>
						<Texto>
							<Texto>ÑANDEJARA CARNES</Texto>
							<Atributos type="list">
							</Atributos>
						</Texto>
					</LineaUsuario>
					<Apertura>
						<Orden>5</Orden>
						<TipoDocumento>DocumentoNoFiscalInterno</TipoDocumento>
						<SubTipoDocumento>CierreX</SubTipoDocumento>
						<CalificadorDocumento>SinCalificador</CalificadorDocumento>
						<Estacion>Ticket</Estacion>
						<TipoAFIP>940</TipoAFIP>
						<POS>00011</POS>
						<Fecha>230130</Fecha>
						<Hora>201421</Hora>
						<NumeroDocumento>1475</NumeroDocumento>
						<NumeroCompleto>00011-00001475</NumeroCompleto>
						<IdentificadorCopia>NoCopias</IdentificadorCopia>
					</Apertura>
					<CierreXDatosGenerales>
						<Orden>6</Orden>
						<SubTipoDocumento>CierreX</SubTipoDocumento>
						<CalificadorDocumento>SinCalificador</CalificadorDocumento>
						<NumeroX>1474</NumeroX>
						<FechaInicio>230130</FechaInicio>
						<HoraInicio>173329</HoraInicio>
						<FechaCierre>230130</FechaCierre>
						<HoraCierre>201421</HoraCierre>
						<TotalDF>35459.34</TotalDF>
						<MontoIVADF>3369.45</MontoIVADF>
						<MontoOtrosTributosDF>0</MontoOtrosTributosDF>
						<CantidadDF>11</CantidadDF>
						<TotalNC>0</TotalNC>
						<MontoIVANC>0</MontoIVANC>
						<MontoOtrosTributosNC>0</MontoOtrosTributosNC>
						<CantidadNC>0</CantidadNC>
						<CantidadDNFH>0</CantidadDNFH>
					</CierreXDatosGenerales>
					<Cierre>
						<Orden>7</Orden>
						<TipoDocumento>DocumentoNoFiscalInterno</TipoDocumento>
						<SubTipoDocumento>CierreX</SubTipoDocumento>
						<CalificadorDocumento>SinCalificador</CalificadorDocumento>
						<Estacion>Ticket</Estacion>
						<Registro>HSHSAB0000009658</Registro>
						<Version>01.00</Version>
						<NumeroDocumento>1475</NumeroDocumento>
						<NumeroCompleto>00011-00001475</NumeroCompleto>
						<Totales>
							<Total>0</Total>
							<TotalBase>0</TotalBase>
							<TotalNoGravado>0</TotalNoGravado>
							<TotalGravado>0</TotalGravado>
							<TotalExento>0</TotalExento>
							<TotalIVA>0</TotalIVA>
							<TotalII>0</TotalII>
							<TotalOtrosTributos>0</TotalOtrosTributos>
							<TotalPagos>0</TotalPagos>
							<OperacionesVenta>0</OperacionesVenta>
							<DiscriminacionIVA type="list">
							</DiscriminacionIVA>
							<DiscriminacionOtrosTributos type="list">
							</DiscriminacionOtrosTributos>
						</Totales>
					</Cierre>
				</Items>
			</Documento>
			<Documento>
				<Orden>12</Orden>
				<Items type="list">
					<AtributosImpresion>
						<Orden>0</Orden>
						<Personalidad>ImpresorFiscal</Personalidad>
						<Producto>SMH/PT-250F 6.02A</Producto>
						<Modelo>Hasar SMH/PT-250F 1.</Modelo>
						<ModeloImpresor>80250-64</ModeloImpresor>
						<Estacion>Ticket</Estacion>
						<AnchoPapel>64</AnchoPapel>
						<AltoPapel>0</AltoPapel>
						<TipoHojaAlto>AltoA4</TipoHojaAlto>
						<TipoHojaAncho>AnchoNormal</TipoHojaAncho>
						<ImprimeLeyendasOpcionales>Sí</ImprimeLeyendasOpcionales>
						<ImprimeCodigos>NoImprimeCodigos</ImprimeCodigos>
						<ImprimeUnidadesMedida>No</ImprimeUnidadesMedida>
						<ImprimeMarcos>No</ImprimeMarcos>
						<ModoEntrenamiento>No</ModoEntrenamiento>
						<SignoMonetario>$</SignoMonetario>
						<UsarColorAlternativo>No</UsarColorAlternativo>
						<ColorAlternativo>Negro</ColorAlternativo>
						<ImprimeQR>Sí</ImprimeQR>
						<TipoInterlineado>InterlineadoNormal</TipoInterlineado>
					</AtributosImpresion>
					<Emisor>
						<Orden>1</Orden>
						<CUIT>20347825604</CUIT>
						<RazonSocial>COLANERI SERGIO ALEJANDRO</RazonSocial>
						<NroRegistro>HSHSAB0000009658</NroRegistro>
						<FechaInicioActividades>20180901</FechaInicioActividades>
						<IngBrutos>20-34782560-4</IngBrutos>
						<TipoEmisor>EmisorInscripto</TipoEmisor>
						<TipoHabilitacion>ComprobantesA</TipoHabilitacion>
						<LimiteM>1000</LimiteM>
					</Emisor>
					<LineaUsuario>
						<Orden>2</Orden>
						<Estacion>Ticket</Estacion>
						<Tipo>OwnerAddress</Tipo>
						<Linea>1</Linea>
						<Texto>
							<Texto>CALLE 16 ESQ 19</Texto>
							<Atributos type="list">
							</Atributos>
						</Texto>
					</LineaUsuario>
					<LineaUsuario>
						<Orden>3</Orden>
						<Estacion>Ticket</Estacion>
						<Tipo>OwnerAddress</Tipo>
						<Linea>2</Linea>
						<Texto>
							<Texto>C.P.(3700)-PCIA. R. S. PEÑA-CHACO</Texto>
							<Atributos type="list">
							</Atributos>
						</Texto>
					</LineaUsuario>
					<LineaUsuario>
						<Orden>4</Orden>
						<Estacion>Ticket</Estacion>
						<Tipo>Fantasy</Tipo>
						<Linea>1</Linea>
						<Texto>
							<Texto>ÑANDEJARA CARNES</Texto>
							<Atributos type="list">
							</Atributos>
						</Texto>
					</LineaUsuario>
					<Apertura>
						<Orden>5</Orden>
						<TipoDocumento>DocumentoNoFiscalInterno</TipoDocumento>
						<SubTipoDocumento>ZFiscal</SubTipoDocumento>
						<CalificadorDocumento>SinCalificador</CalificadorDocumento>
						<Estacion>Ticket</Estacion>
						<TipoAFIP>80</TipoAFIP>
						<POS>00011</POS>
						<Fecha>230130</Fecha>
						<Hora>201427</Hora>
						<NumeroDocumento>1487</NumeroDocumento>
						<NumeroCompleto>00001487</NumeroCompleto>
						<IdentificadorCopia>NoCopias</IdentificadorCopia>
					</Apertura>
					<CierreDiarioEncabezado>
						<Orden>6</Orden>
						<SubTipoDocumento>ZFiscal</SubTipoDocumento>
						<CalificadorDocumento>SinCalificador</CalificadorDocumento>
						<NumeroZeta>1487</NumeroZeta>
						<Remanentes>2163</Remanentes>
						<MemoriaFiscalPorAcabarse>No</MemoriaFiscalPorAcabarse>
						<MemoriaAuditoriaPorAcabarse>No</MemoriaAuditoriaPorAcabarse>
						<CertificadoExpirado>No</CertificadoExpirado>
						<CertificadoPorExpirarse>No</CertificadoPorExpirarse>
						<FechaExpiracionCertificado>231216</FechaExpiracionCertificado>
						<CadenaValidacionExpirada>No</CadenaValidacionExpirada>
						<CadenaValidacionPorExpirarse>No</CadenaValidacionPorExpirarse>
						<FechaExpiracionCadenaValidacion></FechaExpiracionCadenaValidacion>
						<NumeroSecuenciaMemoriaAuditoria>1</NumeroSecuenciaMemoriaAuditoria>
						<BloqueosJornada>0</BloqueosJornada>
						<TotalBloqueos>0</TotalBloqueos>
						<FechaInicio>230130</FechaInicio>
						<HoraInicio>173329</HoraInicio>
						<FechaCierre>230130</FechaCierre>
						<HoraCierre>201421</HoraCierre>
						<FechaJornada>230130</FechaJornada>
						<TipoEmisor>EmisorInscripto</TipoEmisor>
						<TipoHabilitacion>ComprobantesA</TipoHabilitacion>
					</CierreDiarioEncabezado>
					<CierreDiarioContextoTipoComprobante>
						<Orden>7</Orden>
						<TipoComprobante>DocumentoFiscal</TipoComprobante>
						<SubTipoComprobante>Factura</SubTipoComprobante>
						<CalificadorComprobante>B</CalificadorComprobante>
						<Estacion>Ticket</Estacion>
						<ConLeyenda>No</ConLeyenda>
					</CierreDiarioContextoTipoComprobante>
					<CierreDiarioInformacionDocumento>
						<Orden>8</Orden>
						<PrimerComprobante>54745</PrimerComprobante>
						<UltimoComprobante>54755</UltimoComprobante>
						<CantidadEmitidos>11</CantidadEmitidos>
						<CantidadCancelados>0</CantidadCancelados>
					</CierreDiarioInformacionDocumento>
					<CierreDiarioIVA>
						<Orden>9</Orden>
						<TasaIVA>10.5</TasaIVA>
						<TotalBase>0</TotalBase>
						<TotalIVA>3369.45</TotalIVA>
					</CierreDiarioIVA>
					<CierreDiarioTotales>
						<Orden>10</Orden>
						<TotalGravado>32089.89</TotalGravado>
						<TotalNoGravado>0</TotalNoGravado>
						<TotalExento>0</TotalExento>
						<TotalIVA>3369.45</TotalIVA>
						<TotalOtrosTributos>0</TotalOtrosTributos>
						<TotalBonificaciones>0</TotalBonificaciones>
						<TotalFinal>35459.34</TotalFinal>
					</CierreDiarioTotales>
					<CierreDiarioContextoTotales>
						<Orden>11</Orden>
					</CierreDiarioContextoTotales>
					<CierreDiarioInformacionDocumento>
						<Orden>12</Orden>
						<PrimerComprobante>0</PrimerComprobante>
						<UltimoComprobante>0</UltimoComprobante>
						<CantidadEmitidos>11</CantidadEmitidos>
						<CantidadCancelados>0</CantidadCancelados>
					</CierreDiarioInformacionDocumento>
					<CierreDiarioIVA>
						<Orden>13</Orden>
						<TasaIVA>10.5</TasaIVA>
						<TotalBase>0</TotalBase>
						<TotalIVA>3369.45</TotalIVA>
					</CierreDiarioIVA>
					<CierreDiarioTotales>
						<Orden>14</Orden>
						<TotalGravado>32089.89</TotalGravado>
						<TotalNoGravado>0</TotalNoGravado>
						<TotalExento>0</TotalExento>
						<TotalIVA>3369.45</TotalIVA>
						<TotalOtrosTributos>0</TotalOtrosTributos>
						<TotalBonificaciones>0</TotalBonificaciones>
						<TotalFinal>35459.34</TotalFinal>
					</CierreDiarioTotales>
					<CierreDiarioContextoTipoComprobante>
						<Orden>15</Orden>
						<TipoComprobante>DocumentoNoFiscalInterno</TipoComprobante>
						<SubTipoComprobante>CierreX</SubTipoComprobante>
						<CalificadorComprobante>SinCalificador</CalificadorComprobante>
						<Estacion>Ticket</Estacion>
						<ConLeyenda>No</ConLeyenda>
					</CierreDiarioContextoTipoComprobante>
					<CierreDiarioInformacionDocumento>
						<Orden>16</Orden>
						<PrimerComprobante>1475</PrimerComprobante>
						<UltimoComprobante>1475</UltimoComprobante>
						<CantidadEmitidos>1</CantidadEmitidos>
						<CantidadCancelados>0</CantidadCancelados>
					</CierreDiarioInformacionDocumento>
					<CierreDiarioTotales>
						<Orden>17</Orden>
						<TotalGravado>0</TotalGravado>
						<TotalNoGravado>0</TotalNoGravado>
						<TotalExento>0</TotalExento>
						<TotalIVA>0</TotalIVA>
						<TotalOtrosTributos>0</TotalOtrosTributos>
						<TotalBonificaciones>0</TotalBonificaciones>
						<TotalFinal>0</TotalFinal>
					</CierreDiarioTotales>
					<CierreDiarioContextoTotales>
						<Orden>18</Orden>
					</CierreDiarioContextoTotales>
					<CierreDiarioTotales>
						<Orden>19</Orden>
						<TotalGravado>0</TotalGravado>
						<TotalNoGravado>0</TotalNoGravado>
						<TotalExento>0</TotalExento>
						<TotalIVA>0</TotalIVA>
						<TotalOtrosTributos>0</TotalOtrosTributos>
						<TotalBonificaciones>0</TotalBonificaciones>
						<TotalFinal>0</TotalFinal>
					</CierreDiarioTotales>
					<Cierre>
						<Orden>20</Orden>
						<TipoDocumento>DocumentoNoFiscalInterno</TipoDocumento>
						<SubTipoDocumento>ZFiscal</SubTipoDocumento>
						<CalificadorDocumento>SinCalificador</CalificadorDocumento>
						<Estacion>Ticket</Estacion>
						<Registro>HSHSAB0000009658</Registro>
						<Version>01.00</Version>
						<NumeroDocumento>1487</NumeroDocumento>
						<NumeroCompleto>00001487</NumeroCompleto>
						<Totales>
							<Total>0</Total>
							<TotalBase>0</TotalBase>
							<TotalNoGravado>0</TotalNoGravado>
							<TotalGravado>0</TotalGravado>
							<TotalExento>0</TotalExento>
							<TotalIVA>0</TotalIVA>
							<TotalII>0</TotalII>
							<TotalOtrosTributos>0</TotalOtrosTributos>
							<TotalPagos>0</TotalPagos>
							<OperacionesVenta>0</OperacionesVenta>
							<DiscriminacionIVA type="list">
							</DiscriminacionIVA>
							<DiscriminacionOtrosTributos type="list">
							</DiscriminacionOtrosTributos>
						</Totales>
					</Cierre>
				</Items>
			</Documento>
		</Documentos>
	</Jornada>
</Jornada>